{"channel": {"title": "XML Historical Foreign Exchange Rates for Kazakhstani Tenge (KZT) (17 Jan 2020)", "link": "http://www.floatrates.com/currency/kzt/", "xmlLink": "http://www.floatrates.com/daily/kzt.xml", "description": "XML historical foreign exchange rates for Kazakhstani Tenge (KZT) from the Float Rates. Published at 17 Jan 2020.", "language": "en", "baseCurrency": "KZT", "pubDate": "Fri, 17 Jan 2020", "lastBuildDate": "Fri, 17 Jan 2020", "item": [{"title": "1 KZT = 0.002649 USD", "link": "http://www.floatrates.com/kzt/usd/", "description": "1 Kazakhstani Tenge = 0.002649 U.S. Dollar", "pubDate": null, "baseCurrency": "KZT", "baseName": "Kazakhstani Tenge", "targetCurrency": "USD", "targetName": "U.S. Dollar", "exchangeRate": "0.002649", "inverseRate": "377.498330", "inverseDescription": "1 U.S. Dollar = 377.498330 Kazakhstani Tenge"}, {"title": "1 KZT = 0.018178 CNY", "link": "http://www.floatrates.com/kzt/cny/", "description": "1 Kazakhstani Tenge = 0.018178 Chinese Yuan", "pubDate": null, "baseCurrency": "KZT", "baseName": "Kazakhstani Tenge", "targetCurrency": "CNY", "targetName": "Chinese Yuan", "exchangeRate": "0.018178", "inverseRate": "55.011908", "inverseDescription": "1 Chinese Yuan = 55.011908 Kazakhstani Tenge"}, {"title": "1 KZT = 0.291845 JPY", "link": "http://www.floatrates.com/kzt/jpy/", "description": "1 Kazakhstani Tenge = 0.291845 Japanese Yen", "pubDate": null, "baseCurrency": "KZT", "baseName": "Kazakhstani Tenge", "targetCurrency": "JPY", "targetName": "Japanese Yen", "exchangeRate": "0.291845", "inverseRate": "3.426482", "inverseDescription": "1 Japanese Yen = 3.426482 Kazakhstani Tenge"}, {"title": "1 KZT = 0.002383 EUR", "link": "http://www.floatrates.com/kzt/eur/", "description": "1 Kazakhstani Tenge = 0.002383 Euro", "pubDate": null, "baseCurrency": "KZT", "baseName": "Kazakhstani Tenge", "targetCurrency": "EUR", "targetName": "Euro", "exchangeRate": "0.002383", "inverseRate": "419.590815", "inverseDescription": "1 Euro = 419.590815 Kazakhstani Tenge"}, {"title": "1 KZT = 3.072440 KRW", "link": "http://www.floatrates.com/kzt/krw/", "description": "1 Kazakhstani Tenge = 3.072440 South Korean Won", "pubDate": null, "baseCurrency": "KZT", "baseName": "Kazakhstani Tenge", "targetCurrency": "KRW", "targetName": "South Korean Won", "exchangeRate": "3.072440", "inverseRate": "0.325474", "inverseDescription": "1 South Korean Won = 0.325474 Kazakhstani Tenge"}, {"title": "1 KZT = 0.003568 SGD", "link": "http://www.floatrates.com/kzt/sgd/", "description": "1 Kazakhstani Tenge = 0.003568 Singapore Dollar", "pubDate": null, "baseCurrency": "KZT", "baseName": "Kazakhstani Tenge", "targetCurrency": "SGD", "targetName": "Singapore Dollar", "exchangeRate": "0.003568", "inverseRate": "280.287555", "inverseDescription": "1 Singapore Dollar = 280.287555 Kazakhstani Tenge"}, {"title": "1 KZT = 0.003996 NZD", "link": "http://www.floatrates.com/kzt/nzd/", "description": "1 Kazakhstani Tenge = 0.003996 New Zealand Dollar", "pubDate": null, "baseCurrency": "KZT", "baseName": "Kazakhstani Tenge", "targetCurrency": "NZD", "targetName": "New Zealand Dollar", "exchangeRate": "0.003996", "inverseRate": "250.248641", "inverseDescription": "1 New Zealand Dollar = 250.248641 Kazakhstani Tenge"}, {"title": "1 KZT = 0.002030 GBP", "link": "http://www.floatrates.com/kzt/gbp/", "description": "1 Kazakhstani Tenge = 0.002030 U.K. Pound Sterling", "pubDate": null, "baseCurrency": "KZT", "baseName": "Kazakhstani Tenge", "targetCurrency": "GBP", "targetName": "U.K. Pound Sterling", "exchangeRate": "0.002030", "inverseRate": "492.619321", "inverseDescription": "1 U.K. Pound Sterling = 492.619321 Kazakhstani Tenge"}, {"title": "1 KZT = 0.010766 MYR", "link": "http://www.floatrates.com/kzt/myr/", "description": "1 Kazakhstani Tenge = 0.010766 Malaysian Ringgit", "pubDate": null, "baseCurrency": "KZT", "baseName": "Kazakhstani Tenge", "targetCurrency": "MYR", "targetName": "Malaysian Ringgit", "exchangeRate": "0.010766", "inverseRate": "92.883095", "inverseDescription": "1 Malaysian Ringgit = 92.883095 Kazakhstani Tenge"}, {"title": "1 KZT = 0.080637 THB", "link": "http://www.floatrates.com/kzt/thb/", "description": "1 Kazakhstani Tenge = 0.080637 Thai Baht", "pubDate": null, "baseCurrency": "KZT", "baseName": "Kazakhstani Tenge", "targetCurrency": "THB", "targetName": "Thai Baht", "exchangeRate": "0.080637", "inverseRate": "12.401187", "inverseDescription": "1 Thai Baht = 12.401187 Kazakhstani Tenge"}, {"title": "1 KZT = 36.129956 IDR", "link": "http://www.floatrates.com/kzt/idr/", "description": "1 Kazakhstani Tenge = 36.129956 Indonesian Rupiah", "pubDate": null, "baseCurrency": "KZT", "baseName": "Kazakhstani Tenge", "targetCurrency": "IDR", "targetName": "Indonesian Rupiah", "exchangeRate": "36.129956", "inverseRate": "0.027678", "inverseDescription": "1 Indonesian Rupiah = 0.027678 Kazakhstani Tenge"}, {"title": "1 KZT = 0.188185 INR", "link": "http://www.floatrates.com/kzt/inr/", "description": "1 Kazakhstani Tenge = 0.188185 Indian Rupee", "pubDate": null, "baseCurrency": "KZT", "baseName": "Kazakhstani Tenge", "targetCurrency": "INR", "targetName": "Indian Rupee", "exchangeRate": "0.188185", "inverseRate": "5.313906", "inverseDescription": "1 Indian Rupee = 5.313906 Kazakhstani Tenge"}, {"title": "1 KZT = 0.079391 TWD", "link": "http://www.floatrates.com/kzt/twd/", "description": "1 Kazakhstani Tenge = 0.079391 New Taiwan Dollar", "pubDate": null, "baseCurrency": "KZT", "baseName": "Kazakhstani Tenge", "targetCurrency": "TWD", "targetName": "New Taiwan Dollar", "exchangeRate": "0.079391", "inverseRate": "12.595894", "inverseDescription": "1 New Taiwan Dollar  = 12.595894 Kazakhstani Tenge"}, {"title": "1 KZT = 61.451830 VND", "link": "http://www.floatrates.com/kzt/vnd/", "description": "1 Kazakhstani Tenge = 61.451830 Vietnamese Dong", "pubDate": null, "baseCurrency": "KZT", "baseName": "Kazakhstani Tenge", "targetCurrency": "VND", "targetName": "Vietnamese Dong", "exchangeRate": "61.451830", "inverseRate": "0.016273", "inverseDescription": "1 Vietnamese Dong = 0.016273 Kazakhstani Tenge"}, {"title": "1 KZT = 0.020579 HKD", "link": "http://www.floatrates.com/kzt/hkd/", "description": "1 Kazakhstani Tenge = 0.020579 Hong Kong Dollar", "pubDate": null, "baseCurrency": "KZT", "baseName": "Kazakhstani Tenge", "targetCurrency": "HKD", "targetName": "Hong Kong Dollar", "exchangeRate": "0.020579", "inverseRate": "48.593622", "inverseDescription": "1 Hong Kong Dollar = 48.593622 Kazakhstani Tenge"}, {"title": "1 KZT = 0.009032 PGK", "link": "http://www.floatrates.com/kzt/pgk/", "description": "1 Kazakhstani Tenge = 0.009032 Papua New Guinean kina", "pubDate": null, "baseCurrency": "KZT", "baseName": "Kazakhstani Tenge", "targetCurrency": "PGK", "targetName": "Papua New Guinean kina", "exchangeRate": "0.009032", "inverseRate": "110.718902", "inverseDescription": "1 Papua New Guinean kina = 110.718902 Kazakhstani Tenge"}, {"title": "1 KZT = 0.002560 CHF", "link": "http://www.floatrates.com/kzt/chf/", "description": "1 Kazakhstani Tenge = 0.002560 Swiss Franc", "pubDate": null, "baseCurrency": "KZT", "baseName": "Kazakhstani Tenge", "targetCurrency": "CHF", "targetName": "Swiss Franc", "exchangeRate": "0.002560", "inverseRate": "390.619302", "inverseDescription": "1 Swiss Franc = 390.619302 Kazakhstani Tenge"}, {"title": "1 KZT = 0.009734 AED", "link": "http://www.floatrates.com/kzt/aed/", "description": "1 Kazakhstani Tenge = 0.009734 U.A.E Dirham", "pubDate": null, "baseCurrency": "KZT", "baseName": "Kazakhstani Tenge", "targetCurrency": "AED", "targetName": "U.A.E Dirham", "exchangeRate": "0.009734", "inverseRate": "102.727636", "inverseDescription": "1 U.A.E Dirham = 102.727636 Kazakhstani Tenge"}, {"title": "1 KZT = 0.003459 CAD", "link": "http://www.floatrates.com/kzt/cad/", "description": "1 Kazakhstani Tenge = 0.003459 Canadian Dollar", "pubDate": null, "baseCurrency": "KZT", "baseName": "Kazakhstani Tenge", "targetCurrency": "CAD", "targetName": "Canadian Dollar", "exchangeRate": "0.003459", "inverseRate": "289.129380", "inverseDescription": "1 Canadian Dollar = 289.129380 Kazakhstani Tenge"}, {"title": "1 KZT = 0.003844 AUD", "link": "http://www.floatrates.com/kzt/aud/", "description": "1 Kazakhstani Tenge = 0.003844 Australian Dollar", "pubDate": null, "baseCurrency": "KZT", "baseName": "Kazakhstani Tenge", "targetCurrency": "AUD", "targetName": "Australian Dollar", "exchangeRate": "0.003844", "inverseRate": "260.128800", "inverseDescription": "1 Australian Dollar = 260.128800 Kazakhstani Tenge"}, {"title": "1 KZT = 0.089545 NIO", "link": "http://www.floatrates.com/kzt/nio/", "description": "1 Kazakhstani Tenge = 0.089545 Nicaraguan C\u00f3rdoba", "pubDate": null, "baseCurrency": "KZT", "baseName": "Kazakhstani Tenge", "targetCurrency": "NIO", "targetName": "Nicaraguan C\u00f3rdoba", "exchangeRate": "0.089545", "inverseRate": "11.167596", "inverseDescription": "1 Nicaraguan C\u00f3rdoba = 11.167596 Kazakhstani Tenge"}, {"title": "1 KZT = 0.004498 AZN", "link": "http://www.floatrates.com/kzt/azn/", "description": "1 Kazakhstani Tenge = 0.004498 Azerbaijan Manat", "pubDate": null, "baseCurrency": "KZT", "baseName": "Kazakhstani Tenge", "targetCurrency": "AZN", "targetName": "Azerbaijan Manat", "exchangeRate": "0.004498", "inverseRate": "222.323632", "inverseDescription": "1 Azerbaijan Manat = 222.323632 Kazakhstani Tenge"}, {"title": "1 KZT = 1.281457 AMD", "link": "http://www.floatrates.com/kzt/amd/", "description": "1 Kazakhstani Tenge = 1.281457 Armenia Dram", "pubDate": null, "baseCurrency": "KZT", "baseName": "Kazakhstani Tenge", "targetCurrency": "AMD", "targetName": "Armenia Dram", "exchangeRate": "1.281457", "inverseRate": "0.780362", "inverseDescription": "1 Armenia Dram = 0.780362 Kazakhstani Tenge"}, {"title": "1 KZT = 0.005626 BYN", "link": "http://www.floatrates.com/kzt/byn/", "description": "1 Kazakhstani Tenge = 0.005626 Belarussian Ruble", "pubDate": null, "baseCurrency": "KZT", "baseName": "Kazakhstani Tenge", "targetCurrency": "BYN", "targetName": "Belarussian Ruble", "exchangeRate": "0.005626", "inverseRate": "177.738515", "inverseDescription": "1 Belarussian Ruble = 177.738515 Kazakhstani Tenge"}, {"title": "1 KZT = 0.004663 BGN", "link": "http://www.floatrates.com/kzt/bgn/", "description": "1 Kazakhstani Tenge = 0.004663 Bulgarian Lev", "pubDate": null, "baseCurrency": "KZT", "baseName": "Kazakhstani Tenge", "targetCurrency": "BGN", "targetName": "Bulgarian Lev", "exchangeRate": "0.004663", "inverseRate": "214.470145", "inverseDescription": "1 Bulgarian Lev = 214.470145 Kazakhstani Tenge"}, {"title": "1 KZT = 0.011064 BRL", "link": "http://www.floatrates.com/kzt/brl/", "description": "1 Kazakhstani Tenge = 0.011064 Brazilian Real", "pubDate": null, "baseCurrency": "KZT", "baseName": "Kazakhstani Tenge", "targetCurrency": "BRL", "targetName": "Brazilian Real", "exchangeRate": "0.011064", "inverseRate": "90.383127", "inverseDescription": "1 Brazilian Real = 90.383127 Kazakhstani Tenge"}, {"title": "1 KZT = 0.799946 HUF", "link": "http://www.floatrates.com/kzt/huf/", "description": "1 Kazakhstani Tenge = 0.799946 Hungarian Forint", "pubDate": null, "baseCurrency": "KZT", "baseName": "Kazakhstani Tenge", "targetCurrency": "HUF", "targetName": "Hungarian Forint", "exchangeRate": "0.799946", "inverseRate": "1.250085", "inverseDescription": "1 Hungarian Forint = 1.250085 Kazakhstani Tenge"}, {"title": "1 KZT = 0.017818 DKK", "link": "http://www.floatrates.com/kzt/dkk/", "description": "1 Kazakhstani Tenge = 0.017818 Danish Krone", "pubDate": null, "baseCurrency": "KZT", "baseName": "Kazakhstani Tenge", "targetCurrency": "DKK", "targetName": "Danish Krone", "exchangeRate": "0.017818", "inverseRate": "56.124236", "inverseDescription": "1 Danish Krone = 56.124236 Kazakhstani Tenge"}, {"title": "1 KZT = 1.000000 KZT", "link": "http://www.floatrates.com/kzt/kzt/", "description": "1 Kazakhstani Tenge = 1.000000 Kazakhstani Tenge", "pubDate": null, "baseCurrency": "KZT", "baseName": "Kazakhstani Tenge", "targetCurrency": "KZT", "targetName": "Kazakhstani Tenge", "exchangeRate": "1.000000", "inverseRate": "1.000000", "inverseDescription": "1 Kazakhstani Tenge = 1.000000 Kazakhstani Tenge"}, {"title": "1 KZT = 0.186574 KGS", "link": "http://www.floatrates.com/kzt/kgs/", "description": "1 Kazakhstani Tenge = 0.186574 Kyrgyzstan Som", "pubDate": null, "baseCurrency": "KZT", "baseName": "Kazakhstani Tenge", "targetCurrency": "KGS", "targetName": "Kyrgyzstan Som", "exchangeRate": "0.186574", "inverseRate": "5.359816", "inverseDescription": "1 Kyrgyzstan Som = 5.359816 Kazakhstani Tenge"}, {"title": "1 KZT = 0.046330 MDL", "link": "http://www.floatrates.com/kzt/mdl/", "description": "1 Kazakhstani Tenge = 0.046330 Moldova Lei", "pubDate": null, "baseCurrency": "KZT", "baseName": "Kazakhstani Tenge", "targetCurrency": "MDL", "targetName": "Moldova Lei", "exchangeRate": "0.046330", "inverseRate": "21.584468", "inverseDescription": "1 Moldova Lei = 21.584468 Kazakhstani Tenge"}, {"title": "1 KZT = 0.009342 TMT", "link": "http://www.floatrates.com/kzt/tmt/", "description": "1 Kazakhstani Tenge = 0.009342 New Turkmenistan Manat", "pubDate": null, "baseCurrency": "KZT", "baseName": "Kazakhstani Tenge", "targetCurrency": "TMT", "targetName": "New Turkmenistan Manat", "exchangeRate": "0.009342", "inverseRate": "107.043558", "inverseDescription": "1 New Turkmenistan Manat = 107.043558 Kazakhstani Tenge"}, {"title": "1 KZT = 0.023588 NOK", "link": "http://www.floatrates.com/kzt/nok/", "description": "1 Kazakhstani Tenge = 0.023588 Norwegian Krone", "pubDate": null, "baseCurrency": "KZT", "baseName": "Kazakhstani Tenge", "targetCurrency": "NOK", "targetName": "Norwegian Krone", "exchangeRate": "0.023588", "inverseRate": "42.394946", "inverseDescription": "1 Norwegian Krone = 42.394946 Kazakhstani Tenge"}, {"title": "1 KZT = 0.010089 PLN", "link": "http://www.floatrates.com/kzt/pln/", "description": "1 Kazakhstani Tenge = 0.010089 Polish Zloty", "pubDate": null, "baseCurrency": "KZT", "baseName": "Kazakhstani Tenge", "targetCurrency": "PLN", "targetName": "Polish Zloty", "exchangeRate": "0.010089", "inverseRate": "99.120002", "inverseDescription": "1 Polish Zloty = 99.120002 Kazakhstani Tenge"}, {"title": "1 KZT = 0.011396 RON", "link": "http://www.floatrates.com/kzt/ron/", "description": "1 Kazakhstani Tenge = 0.011396 Romanian New Leu", "pubDate": null, "baseCurrency": "KZT", "baseName": "Kazakhstani Tenge", "targetCurrency": "RON", "targetName": "Romanian New Leu", "exchangeRate": "0.011396", "inverseRate": "87.749622", "inverseDescription": "1 Romanian New Leu = 87.749622 Kazakhstani Tenge"}, {"title": "1 KZT = 0.025898 TJS", "link": "http://www.floatrates.com/kzt/tjs/", "description": "1 Kazakhstani Tenge = 0.025898 Tajikistan Ruble", "pubDate": null, "baseCurrency": "KZT", "baseName": "Kazakhstani Tenge", "targetCurrency": "TJS", "targetName": "Tajikistan Ruble", "exchangeRate": "0.025898", "inverseRate": "38.612403", "inverseDescription": "1 Tajikistan Ruble = 38.612403 Kazakhstani Tenge"}, {"title": "1 KZT = 0.015596 TRY", "link": "http://www.floatrates.com/kzt/try/", "description": "1 Kazakhstani Tenge = 0.015596 Turkish Lira", "pubDate": null, "baseCurrency": "KZT", "baseName": "Kazakhstani Tenge", "targetCurrency": "TRY", "targetName": "Turkish Lira", "exchangeRate": "0.015596", "inverseRate": "64.118726", "inverseDescription": "1 Turkish Lira = 64.118726 Kazakhstani Tenge"}, {"title": "1 KZT = 25.471196 UZS", "link": "http://www.floatrates.com/kzt/uzs/", "description": "1 Kazakhstani Tenge = 25.471196 Uzbekistan Sum", "pubDate": null, "baseCurrency": "KZT", "baseName": "Kazakhstani Tenge", "targetCurrency": "UZS", "targetName": "Uzbekistan Sum", "exchangeRate": "25.471196", "inverseRate": "0.039260", "inverseDescription": "1 Uzbekistan Sum = 0.039260 Kazakhstani Tenge"}, {"title": "1 KZT = 0.064307 UAH", "link": "http://www.floatrates.com/kzt/uah/", "description": "1 Kazakhstani Tenge = 0.064307 Ukrainian Hryvnia", "pubDate": null, "baseCurrency": "KZT", "baseName": "Kazakhstani Tenge", "targetCurrency": "UAH", "targetName": "Ukrainian Hryvnia", "exchangeRate": "0.064307", "inverseRate": "15.550359", "inverseDescription": "1 Ukrainian Hryvnia = 15.550359 Kazakhstani Tenge"}, {"title": "1 KZT = 0.059964 CZK", "link": "http://www.floatrates.com/kzt/czk/", "description": "1 Kazakhstani Tenge = 0.059964 Czech Koruna", "pubDate": null, "baseCurrency": "KZT", "baseName": "Kazakhstani Tenge", "targetCurrency": "CZK", "targetName": "Czech Koruna", "exchangeRate": "0.059964", "inverseRate": "16.676683", "inverseDescription": "1 Czech Koruna = 16.676683 Kazakhstani Tenge"}, {"title": "1 KZT = 0.025162 SEK", "link": "http://www.floatrates.com/kzt/sek/", "description": "1 Kazakhstani Tenge = 0.025162 Swedish Krona", "pubDate": null, "baseCurrency": "KZT", "baseName": "Kazakhstani Tenge", "targetCurrency": "SEK", "targetName": "Swedish Krona", "exchangeRate": "0.025162", "inverseRate": "39.742521", "inverseDescription": "1 Swedish Krona = 39.742521 Kazakhstani Tenge"}, {"title": "1 KZT = 0.038226 ZAR", "link": "http://www.floatrates.com/kzt/zar/", "description": "1 Kazakhstani Tenge = 0.038226 South African Rand", "pubDate": null, "baseCurrency": "KZT", "baseName": "Kazakhstani Tenge", "targetCurrency": "ZAR", "targetName": "South African Rand", "exchangeRate": "0.038226", "inverseRate": "26.160403", "inverseDescription": "1 South African Rand = 26.160403 Kazakhstani Tenge"}, {"title": "1 KZT = 0.162985 RUB", "link": "http://www.floatrates.com/kzt/rub/", "description": "1 Kazakhstani Tenge = 0.162985 Russian Rouble", "pubDate": null, "baseCurrency": "KZT", "baseName": "Kazakhstani Tenge", "targetCurrency": "RUB", "targetName": "Russian Rouble", "exchangeRate": "0.162985", "inverseRate": "6.135544", "inverseDescription": "1 Russian Rouble = 6.135544 Kazakhstani Tenge"}, {"title": "1 KZT = 0.041992 EGP", "link": "http://www.floatrates.com/kzt/egp/", "description": "1 Kazakhstani Tenge = 0.041992 Egyptian Pound", "pubDate": null, "baseCurrency": "KZT", "baseName": "Kazakhstani Tenge", "targetCurrency": "EGP", "targetName": "Egyptian Pound", "exchangeRate": "0.041992", "inverseRate": "23.813919", "inverseDescription": "1 Egyptian Pound = 23.813919 Kazakhstani Tenge"}, {"title": "1 KZT = 0.017734 HRK", "link": "http://www.floatrates.com/kzt/hrk/", "description": "1 Kazakhstani Tenge = 0.017734 Croatian Kuna", "pubDate": null, "baseCurrency": "KZT", "baseName": "Kazakhstani Tenge", "targetCurrency": "HRK", "targetName": "Croatian Kuna", "exchangeRate": "0.017734", "inverseRate": "56.387308", "inverseDescription": "1 Croatian Kuna = 56.387308 Kazakhstani Tenge"}, {"title": "1 KZT = 0.049636 MXN", "link": "http://www.floatrates.com/kzt/mxn/", "description": "1 Kazakhstani Tenge = 0.049636 Mexican Peso", "pubDate": null, "baseCurrency": "KZT", "baseName": "Kazakhstani Tenge", "targetCurrency": "MXN", "targetName": "Mexican Peso", "exchangeRate": "0.049636", "inverseRate": "20.146719", "inverseDescription": "1 Mexican Peso = 20.146719 Kazakhstani Tenge"}, {"title": "1 KZT = 0.281851 RSD", "link": "http://www.floatrates.com/kzt/rsd/", "description": "1 Kazakhstani Tenge = 0.281851 Serbian Dinar", "pubDate": null, "baseCurrency": "KZT", "baseName": "Kazakhstani Tenge", "targetCurrency": "RSD", "targetName": "Serbian Dinar", "exchangeRate": "0.281851", "inverseRate": "3.547972", "inverseDescription": "1 Serbian Dinar = 3.547972 Kazakhstani Tenge"}, {"title": "1 KZT = 0.009151 ILS", "link": "http://www.floatrates.com/kzt/ils/", "description": "1 Kazakhstani Tenge = 0.009151 Israeli New Sheqel", "pubDate": null, "baseCurrency": "KZT", "baseName": "Kazakhstani Tenge", "targetCurrency": "ILS", "targetName": "Israeli New Sheqel", "exchangeRate": "0.009151", "inverseRate": "109.279248", "inverseDescription": "1 Israeli New Sheqel = 109.279248 Kazakhstani Tenge"}, {"title": "1 KZT = 0.001880 JOD", "link": "http://www.floatrates.com/kzt/jod/", "description": "1 Kazakhstani Tenge = 0.001880 Jordanian Dinar", "pubDate": null, "baseCurrency": "KZT", "baseName": "Kazakhstani Tenge", "targetCurrency": "JOD", "targetName": "Jordanian Dinar", "exchangeRate": "0.001880", "inverseRate": "531.987316", "inverseDescription": "1 Jordanian Dinar = 531.987316 Kazakhstani Tenge"}, {"title": "1 KZT = 4.038286 LBP", "link": "http://www.floatrates.com/kzt/lbp/", "description": "1 Kazakhstani Tenge = 4.038286 Lebanese Pound", "pubDate": null, "baseCurrency": "KZT", "baseName": "Kazakhstani Tenge", "targetCurrency": "LBP", "targetName": "Lebanese Pound", "exchangeRate": "4.038286", "inverseRate": "0.247630", "inverseDescription": "1 Lebanese Pound = 0.247630 Kazakhstani Tenge"}, {"title": "1 KZT = 0.327541 ISK", "link": "http://www.floatrates.com/kzt/isk/", "description": "1 Kazakhstani Tenge = 0.327541 Icelandic Krona", "pubDate": null, "baseCurrency": "KZT", "baseName": "Kazakhstani Tenge", "targetCurrency": "ISK", "targetName": "Icelandic Krona", "exchangeRate": "0.327541", "inverseRate": "3.053052", "inverseDescription": "1 Icelandic Krona = 3.053052 Kazakhstani Tenge"}, {"title": "1 KZT = 2.041990 CLP", "link": "http://www.floatrates.com/kzt/clp/", "description": "1 Kazakhstani Tenge = 2.041990 Chilean Peso", "pubDate": null, "baseCurrency": "KZT", "baseName": "Kazakhstani Tenge", "targetCurrency": "CLP", "targetName": "Chilean Peso", "exchangeRate": "2.041990", "inverseRate": "0.489718", "inverseDescription": "1 Chilean Peso = 0.489718 Kazakhstani Tenge"}, {"title": "1 KZT = 0.135047 PHP", "link": "http://www.floatrates.com/kzt/php/", "description": "1 Kazakhstani Tenge = 0.135047 Philippine Peso", "pubDate": null, "baseCurrency": "KZT", "baseName": "Kazakhstani Tenge", "targetCurrency": "PHP", "targetName": "Philippine Peso", "exchangeRate": "0.135047", "inverseRate": "7.404822", "inverseDescription": "1 Philippine Peso = 7.404822 Kazakhstani Tenge"}, {"title": "1 KZT = 0.206699 AFN", "link": "http://www.floatrates.com/kzt/afn/", "description": "1 Kazakhstani Tenge = 0.206699 Afghan afghani", "pubDate": null, "baseCurrency": "KZT", "baseName": "Kazakhstani Tenge", "targetCurrency": "AFN", "targetName": "Afghan afghani", "exchangeRate": "0.206699", "inverseRate": "4.837947", "inverseDescription": "1 Afghan afghani = 4.837947 Kazakhstani Tenge"}, {"title": "1 KZT = 9.853675 MGA", "link": "http://www.floatrates.com/kzt/mga/", "description": "1 Kazakhstani Tenge = 9.853675 Malagasy ariary", "pubDate": null, "baseCurrency": "KZT", "baseName": "Kazakhstani Tenge", "targetCurrency": "MGA", "targetName": "Malagasy ariary", "exchangeRate": "9.853675", "inverseRate": "0.101485", "inverseDescription": "1 Malagasy ariary = 0.101485 Kazakhstani Tenge"}, {"title": "1 KZT = 0.002653 PAB", "link": "http://www.floatrates.com/kzt/pab/", "description": "1 Kazakhstani Tenge = 0.002653 Panamanian Balboa", "pubDate": null, "baseCurrency": "KZT", "baseName": "Kazakhstani Tenge", "targetCurrency": "PAB", "targetName": "Panamanian Balboa", "exchangeRate": "0.002653", "inverseRate": "376.893190", "inverseDescription": "1 Panamanian Balboa = 376.893190 Kazakhstani Tenge"}, {"title": "1 KZT = 0.084637 ETB", "link": "http://www.floatrates.com/kzt/etb/", "description": "1 Kazakhstani Tenge = 0.084637 Ethiopian birr", "pubDate": null, "baseCurrency": "KZT", "baseName": "Kazakhstani Tenge", "targetCurrency": "ETB", "targetName": "Ethiopian birr", "exchangeRate": "0.084637", "inverseRate": "11.815113", "inverseDescription": "1 Ethiopian birr = 11.815113 Kazakhstani Tenge"}, {"title": "1 KZT = 180.161630 VES", "link": "http://www.floatrates.com/kzt/ves/", "description": "1 Kazakhstani Tenge = 180.161630 Venezuelan Bolivar", "pubDate": null, "baseCurrency": "KZT", "baseName": "Kazakhstani Tenge", "targetCurrency": "VES", "targetName": "Venezuelan Bolivar", "exchangeRate": "180.161630", "inverseRate": "0.005551", "inverseDescription": "1 Venezuelan Bolivar = 0.005551 Kazakhstani Tenge"}, {"title": "1 KZT = 0.018332 BOB", "link": "http://www.floatrates.com/kzt/bob/", "description": "1 Kazakhstani Tenge = 0.018332 Bolivian Boliviano", "pubDate": null, "baseCurrency": "KZT", "baseName": "Kazakhstani Tenge", "targetCurrency": "BOB", "targetName": "Bolivian Boliviano", "exchangeRate": "0.018332", "inverseRate": "54.549752", "inverseDescription": "1 Bolivian Boliviano = 54.549752 Kazakhstani Tenge"}, {"title": "1 KZT = 1.518241 CRC", "link": "http://www.floatrates.com/kzt/crc/", "description": "1 Kazakhstani Tenge = 1.518241 Costa Rican Col\u00f3n", "pubDate": null, "baseCurrency": "KZT", "baseName": "Kazakhstani Tenge", "targetCurrency": "CRC", "targetName": "Costa Rican Col\u00f3n", "exchangeRate": "1.518241", "inverseRate": "0.658657", "inverseDescription": "1 Costa Rican Col\u00f3n = 0.658657 Kazakhstani Tenge"}, {"title": "1 KZT = 0.023232 SVC", "link": "http://www.floatrates.com/kzt/svc/", "description": "1 Kazakhstani Tenge = 0.023232 Salvadoran colon", "pubDate": null, "baseCurrency": "KZT", "baseName": "Kazakhstani Tenge", "targetCurrency": "SVC", "targetName": "Salvadoran colon", "exchangeRate": "0.023232", "inverseRate": "43.044313", "inverseDescription": "1 Salvadoran colon = 43.044313 Kazakhstani Tenge"}, {"title": "1 KZT = 0.136037 GMD", "link": "http://www.floatrates.com/kzt/gmd/", "description": "1 Kazakhstani Tenge = 0.136037 Gambian dalasi", "pubDate": null, "baseCurrency": "KZT", "baseName": "Kazakhstani Tenge", "targetCurrency": "GMD", "targetName": "Gambian dalasi", "exchangeRate": "0.136037", "inverseRate": "7.350965", "inverseDescription": "1 Gambian dalasi = 7.350965 Kazakhstani Tenge"}, {"title": "1 KZT = 0.146631 MKD", "link": "http://www.floatrates.com/kzt/mkd/", "description": "1 Kazakhstani Tenge = 0.146631 Macedonian denar", "pubDate": null, "baseCurrency": "KZT", "baseName": "Kazakhstani Tenge", "targetCurrency": "MKD", "targetName": "Macedonian denar", "exchangeRate": "0.146631", "inverseRate": "6.819830", "inverseDescription": "1 Macedonian denar = 6.819830 Kazakhstani Tenge"}, {"title": "1 KZT = 0.316927 DZD", "link": "http://www.floatrates.com/kzt/dzd/", "description": "1 Kazakhstani Tenge = 0.316927 Algerian Dinar", "pubDate": null, "baseCurrency": "KZT", "baseName": "Kazakhstani Tenge", "targetCurrency": "DZD", "targetName": "Algerian Dinar", "exchangeRate": "0.316927", "inverseRate": "3.155304", "inverseDescription": "1 Algerian Dinar = 3.155304 Kazakhstani Tenge"}, {"title": "1 KZT = 0.001000 BHD", "link": "http://www.floatrates.com/kzt/bhd/", "description": "1 Kazakhstani Tenge = 0.001000 Bahrain Dinar", "pubDate": null, "baseCurrency": "KZT", "baseName": "Kazakhstani Tenge", "targetCurrency": "BHD", "targetName": "Bahrain Dinar", "exchangeRate": "0.001000", "inverseRate": "1,000.048659", "inverseDescription": "1 Bahrain Dinar = 1,000.048659 Kazakhstani Tenge"}, {"title": "1 KZT = 3.197851 IQD", "link": "http://www.floatrates.com/kzt/iqd/", "description": "1 Kazakhstani Tenge = 3.197851 Iraqi dinar", "pubDate": null, "baseCurrency": "KZT", "baseName": "Kazakhstani Tenge", "targetCurrency": "IQD", "targetName": "Iraqi dinar", "exchangeRate": "3.197851", "inverseRate": "0.312710", "inverseDescription": "1 Iraqi dinar = 0.312710 Kazakhstani Tenge"}, {"title": "1 KZT = 0.000803 KWD", "link": "http://www.floatrates.com/kzt/kwd/", "description": "1 Kazakhstani Tenge = 0.000803 Kuwaiti Dinar", "pubDate": null, "baseCurrency": "KZT", "baseName": "Kazakhstani Tenge", "targetCurrency": "KWD", "targetName": "Kuwaiti Dinar", "exchangeRate": "0.000803", "inverseRate": "1,244.878314", "inverseDescription": "1 Kuwaiti Dinar = 1,244.878314 Kazakhstani Tenge"}, {"title": "1 KZT = 0.003760 LYD", "link": "http://www.floatrates.com/kzt/lyd/", "description": "1 Kazakhstani Tenge = 0.003760 Libyan Dinar", "pubDate": null, "baseCurrency": "KZT", "baseName": "Kazakhstani Tenge", "targetCurrency": "LYD", "targetName": "Libyan Dinar", "exchangeRate": "0.003760", "inverseRate": "265.984445", "inverseDescription": "1 Libyan Dinar = 265.984445 Kazakhstani Tenge"}, {"title": "1 KZT = 0.007575 TND", "link": "http://www.floatrates.com/kzt/tnd/", "description": "1 Kazakhstani Tenge = 0.007575 Tunisian Dinar", "pubDate": null, "baseCurrency": "KZT", "baseName": "Kazakhstani Tenge", "targetCurrency": "TND", "targetName": "Tunisian Dinar", "exchangeRate": "0.007575", "inverseRate": "132.019366", "inverseDescription": "1 Tunisian Dinar = 132.019366 Kazakhstani Tenge"}, {"title": "1 KZT = 0.025729 MAD", "link": "http://www.floatrates.com/kzt/mad/", "description": "1 Kazakhstani Tenge = 0.025729 Moroccan Dirham", "pubDate": null, "baseCurrency": "KZT", "baseName": "Kazakhstani Tenge", "targetCurrency": "MAD", "targetName": "Moroccan Dirham", "exchangeRate": "0.025729", "inverseRate": "38.866698", "inverseDescription": "1 Moroccan Dirham = 38.866698 Kazakhstani Tenge"}, {"title": "1 KZT = 0.059717 STN", "link": "http://www.floatrates.com/kzt/stn/", "description": "1 Kazakhstani Tenge = 0.059717 S\u00e3o Tom\u00e9 and Pr\u00edncipe Dobra", "pubDate": null, "baseCurrency": "KZT", "baseName": "Kazakhstani Tenge", "targetCurrency": "STN", "targetName": "S\u00e3o Tom\u00e9 and Pr\u00edncipe Dobra", "exchangeRate": "0.059717", "inverseRate": "16.745518", "inverseDescription": "1 S\u00e3o Tom\u00e9 and Pr\u00edncipe Dobra = 16.745518 Kazakhstani Tenge"}, {"title": "1 KZT = 0.002653 BSD", "link": "http://www.floatrates.com/kzt/bsd/", "description": "1 Kazakhstani Tenge = 0.002653 Bahamian Dollar", "pubDate": null, "baseCurrency": "KZT", "baseName": "Kazakhstani Tenge", "targetCurrency": "BSD", "targetName": "Bahamian Dollar", "exchangeRate": "0.002653", "inverseRate": "376.893190", "inverseDescription": "1 Bahamian Dollar = 376.893190 Kazakhstani Tenge"}, {"title": "1 KZT = 0.005301 BBD", "link": "http://www.floatrates.com/kzt/bbd/", "description": "1 Kazakhstani Tenge = 0.005301 Barbadian Dollar", "pubDate": null, "baseCurrency": "KZT", "baseName": "Kazakhstani Tenge", "targetCurrency": "BBD", "targetName": "Barbadian Dollar", "exchangeRate": "0.005301", "inverseRate": "188.647701", "inverseDescription": "1 Barbadian Dollar = 188.647701 Kazakhstani Tenge"}, {"title": "1 KZT = 0.005349 BZD", "link": "http://www.floatrates.com/kzt/bzd/", "description": "1 Kazakhstani Tenge = 0.005349 Belize dollar", "pubDate": null, "baseCurrency": "KZT", "baseName": "Kazakhstani Tenge", "targetCurrency": "BZD", "targetName": "Belize dollar", "exchangeRate": "0.005349", "inverseRate": "186.958545", "inverseDescription": "1 Belize dollar = 186.958545 Kazakhstani Tenge"}, {"title": "1 KZT = 0.003568 BND", "link": "http://www.floatrates.com/kzt/bnd/", "description": "1 Kazakhstani Tenge = 0.003568 Brunei Dollar", "pubDate": null, "baseCurrency": "KZT", "baseName": "Kazakhstani Tenge", "targetCurrency": "BND", "targetName": "Brunei Dollar", "exchangeRate": "0.003568", "inverseRate": "280.282129", "inverseDescription": "1 Brunei Dollar = 280.282129 Kazakhstani Tenge"}, {"title": "1 KZT = 0.005744 FJD", "link": "http://www.floatrates.com/kzt/fjd/", "description": "1 Kazakhstani Tenge = 0.005744 Fiji Dollar", "pubDate": null, "baseCurrency": "KZT", "baseName": "Kazakhstani Tenge", "targetCurrency": "FJD", "targetName": "Fiji Dollar", "exchangeRate": "0.005744", "inverseRate": "174.091877", "inverseDescription": "1 Fiji Dollar = 174.091877 Kazakhstani Tenge"}, {"title": "1 KZT = 0.555144 GYD", "link": "http://www.floatrates.com/kzt/gyd/", "description": "1 Kazakhstani Tenge = 0.555144 Guyanese dollar", "pubDate": null, "baseCurrency": "KZT", "baseName": "Kazakhstani Tenge", "targetCurrency": "GYD", "targetName": "Guyanese dollar", "exchangeRate": "0.555144", "inverseRate": "1.801334", "inverseDescription": "1 Guyanese dollar = 1.801334 Kazakhstani Tenge"}, {"title": "1 KZT = 0.352458 JMD", "link": "http://www.floatrates.com/kzt/jmd/", "description": "1 Kazakhstani Tenge = 0.352458 Jamaican Dollar", "pubDate": null, "baseCurrency": "KZT", "baseName": "Kazakhstani Tenge", "targetCurrency": "JMD", "targetName": "Jamaican Dollar", "exchangeRate": "0.352458", "inverseRate": "2.837214", "inverseDescription": "1 Jamaican Dollar = 2.837214 Kazakhstani Tenge"}, {"title": "1 KZT = 0.504015 LRD", "link": "http://www.floatrates.com/kzt/lrd/", "description": "1 Kazakhstani Tenge = 0.504015 Liberian dollar", "pubDate": null, "baseCurrency": "KZT", "baseName": "Kazakhstani Tenge", "targetCurrency": "LRD", "targetName": "Liberian dollar", "exchangeRate": "0.504015", "inverseRate": "1.984066", "inverseDescription": "1 Liberian dollar = 1.984066 Kazakhstani Tenge"}, {"title": "1 KZT = 0.038241 NAD", "link": "http://www.floatrates.com/kzt/nad/", "description": "1 Kazakhstani Tenge = 0.038241 Namibian dollar", "pubDate": null, "baseCurrency": "KZT", "baseName": "Kazakhstani Tenge", "targetCurrency": "NAD", "targetName": "Namibian dollar", "exchangeRate": "0.038241", "inverseRate": "26.149991", "inverseDescription": "1 Namibian dollar = 26.149991 Kazakhstani Tenge"}, {"title": "1 KZT = 0.019835 SRD", "link": "http://www.floatrates.com/kzt/srd/", "description": "1 Kazakhstani Tenge = 0.019835 Surinamese dollar", "pubDate": null, "baseCurrency": "KZT", "baseName": "Kazakhstani Tenge", "targetCurrency": "SRD", "targetName": "Surinamese dollar", "exchangeRate": "0.019835", "inverseRate": "50.415119", "inverseDescription": "1 Surinamese dollar = 50.415119 Kazakhstani Tenge"}, {"title": "1 KZT = 0.017930 TTD", "link": "http://www.floatrates.com/kzt/ttd/", "description": "1 Kazakhstani Tenge = 0.017930 Trinidad Tobago Dollar", "pubDate": null, "baseCurrency": "KZT", "baseName": "Kazakhstani Tenge", "targetCurrency": "TTD", "targetName": "Trinidad Tobago Dollar", "exchangeRate": "0.017930", "inverseRate": "55.772097", "inverseDescription": "1 Trinidad Tobago Dollar = 55.772097 Kazakhstani Tenge"}, {"title": "1 KZT = 0.007188 XCD", "link": "http://www.floatrates.com/kzt/xcd/", "description": "1 Kazakhstani Tenge = 0.007188 East Caribbean Dollar", "pubDate": null, "baseCurrency": "KZT", "baseName": "Kazakhstani Tenge", "targetCurrency": "XCD", "targetName": "East Caribbean Dollar", "exchangeRate": "0.007188", "inverseRate": "139.112792", "inverseDescription": "1 East Caribbean Dollar = 139.112792 Kazakhstani Tenge"}, {"title": "1 KZT = 0.021507 SBD", "link": "http://www.floatrates.com/kzt/sbd/", "description": "1 Kazakhstani Tenge = 0.021507 Solomon Islands dollar", "pubDate": null, "baseCurrency": "KZT", "baseName": "Kazakhstani Tenge", "targetCurrency": "SBD", "targetName": "Solomon Islands dollar", "exchangeRate": "0.021507", "inverseRate": "46.496588", "inverseDescription": "1 Solomon Islands dollar = 46.496588 Kazakhstani Tenge"}, {"title": "1 KZT = 0.263882 CVE", "link": "http://www.floatrates.com/kzt/cve/", "description": "1 Kazakhstani Tenge = 0.263882 Cape Verde escudo", "pubDate": null, "baseCurrency": "KZT", "baseName": "Kazakhstani Tenge", "targetCurrency": "CVE", "targetName": "Cape Verde escudo", "exchangeRate": "0.263882", "inverseRate": "3.789566", "inverseDescription": "1 Cape Verde escudo = 3.789566 Kazakhstani Tenge"}, {"title": "1 KZT = 0.004803 AWG", "link": "http://www.floatrates.com/kzt/awg/", "description": "1 Kazakhstani Tenge = 0.004803 Aruban florin", "pubDate": null, "baseCurrency": "KZT", "baseName": "Kazakhstani Tenge", "targetCurrency": "AWG", "targetName": "Aruban florin", "exchangeRate": "0.004803", "inverseRate": "208.197973", "inverseDescription": "1 Aruban florin = 208.197973 Kazakhstani Tenge"}, {"title": "1 KZT = 4.992724 BIF", "link": "http://www.floatrates.com/kzt/bif/", "description": "1 Kazakhstani Tenge = 4.992724 Burundian franc", "pubDate": null, "baseCurrency": "KZT", "baseName": "Kazakhstani Tenge", "targetCurrency": "BIF", "targetName": "Burundian franc", "exchangeRate": "4.992724", "inverseRate": "0.200291", "inverseDescription": "1 Burundian franc = 0.200291 Kazakhstani Tenge"}, {"title": "1 KZT = 1.564116 XOF", "link": "http://www.floatrates.com/kzt/xof/", "description": "1 Kazakhstani Tenge = 1.564116 West African CFA Franc", "pubDate": null, "baseCurrency": "KZT", "baseName": "Kazakhstani Tenge", "targetCurrency": "XOF", "targetName": "West African CFA Franc", "exchangeRate": "1.564116", "inverseRate": "0.639339", "inverseDescription": "1 West African CFA Franc = 0.639339 Kazakhstani Tenge"}, {"title": "1 KZT = 1.566761 XAF", "link": "http://www.floatrates.com/kzt/xaf/", "description": "1 Kazakhstani Tenge = 1.566761 Central African CFA Franc", "pubDate": null, "baseCurrency": "KZT", "baseName": "Kazakhstani Tenge", "targetCurrency": "XAF", "targetName": "Central African CFA Franc", "exchangeRate": "1.566761", "inverseRate": "0.638260", "inverseDescription": "1 Central African CFA Franc = 0.638260 Kazakhstani Tenge"}, {"title": "1 KZT = 0.284562 XPF", "link": "http://www.floatrates.com/kzt/xpf/", "description": "1 Kazakhstani Tenge = 0.284562 CFP Franc", "pubDate": null, "baseCurrency": "KZT", "baseName": "Kazakhstani Tenge", "targetCurrency": "XPF", "targetName": "CFP Franc", "exchangeRate": "0.284562", "inverseRate": "3.514178", "inverseDescription": "1 CFP Franc = 3.514178 Kazakhstani Tenge"}, {"title": "1 KZT = 0.472389 DJF", "link": "http://www.floatrates.com/kzt/djf/", "description": "1 Kazakhstani Tenge = 0.472389 Djiboutian franc", "pubDate": null, "baseCurrency": "KZT", "baseName": "Kazakhstani Tenge", "targetCurrency": "DJF", "targetName": "Djiboutian franc", "exchangeRate": "0.472389", "inverseRate": "2.116899", "inverseDescription": "1 Djiboutian franc = 2.116899 Kazakhstani Tenge"}, {"title": "1 KZT = 25.263934 GNF", "link": "http://www.floatrates.com/kzt/gnf/", "description": "1 Kazakhstani Tenge = 25.263934 Guinean franc", "pubDate": null, "baseCurrency": "KZT", "baseName": "Kazakhstani Tenge", "targetCurrency": "GNF", "targetName": "Guinean franc", "exchangeRate": "25.263934", "inverseRate": "0.039582", "inverseDescription": "1 Guinean franc = 0.039582 Kazakhstani Tenge"}, {"title": "1 KZT = 1.178019 KMF", "link": "http://www.floatrates.com/kzt/kmf/", "description": "1 Kazakhstani Tenge = 1.178019 \tComoro franc", "pubDate": null, "baseCurrency": "KZT", "baseName": "Kazakhstani Tenge", "targetCurrency": "KMF", "targetName": "Comoro franc", "exchangeRate": "1.178019", "inverseRate": "0.848883", "inverseDescription": "1 \tComoro franc = 0.848883 Kazakhstani Tenge"}, {"title": "1 KZT = 4.478147 CDF", "link": "http://www.floatrates.com/kzt/cdf/", "description": "1 Kazakhstani Tenge = 4.478147 Congolese franc", "pubDate": null, "baseCurrency": "KZT", "baseName": "Kazakhstani Tenge", "targetCurrency": "CDF", "targetName": "Congolese franc", "exchangeRate": "4.478147", "inverseRate": "0.223307", "inverseDescription": "1 Congolese franc = 0.223307 Kazakhstani Tenge"}, {"title": "1 KZT = 2.518189 RWF", "link": "http://www.floatrates.com/kzt/rwf/", "description": "1 Kazakhstani Tenge = 2.518189 Rwandan franc", "pubDate": null, "baseCurrency": "KZT", "baseName": "Kazakhstani Tenge", "targetCurrency": "RWF", "targetName": "Rwandan franc", "exchangeRate": "2.518189", "inverseRate": "0.397111", "inverseDescription": "1 Rwandan franc = 0.397111 Kazakhstani Tenge"}, {"title": "1 KZT = 0.002042 GIP", "link": "http://www.floatrates.com/kzt/gip/", "description": "1 Kazakhstani Tenge = 0.002042 Gibraltar pound", "pubDate": null, "baseCurrency": "KZT", "baseName": "Kazakhstani Tenge", "targetCurrency": "GIP", "targetName": "Gibraltar pound", "exchangeRate": "0.002042", "inverseRate": "489.637744", "inverseDescription": "1 Gibraltar pound = 489.637744 Kazakhstani Tenge"}, {"title": "1 KZT = 0.423276 SSP", "link": "http://www.floatrates.com/kzt/ssp/", "description": "1 Kazakhstani Tenge = 0.423276 South Sudanese pound", "pubDate": null, "baseCurrency": "KZT", "baseName": "Kazakhstani Tenge", "targetCurrency": "SSP", "targetName": "South Sudanese pound", "exchangeRate": "0.423276", "inverseRate": "2.362527", "inverseDescription": "1 South Sudanese pound = 2.362527 Kazakhstani Tenge"}, {"title": "1 KZT = 0.120147 SDG", "link": "http://www.floatrates.com/kzt/sdg/", "description": "1 Kazakhstani Tenge = 0.120147 Sudanese pound", "pubDate": null, "baseCurrency": "KZT", "baseName": "Kazakhstani Tenge", "targetCurrency": "SDG", "targetName": "Sudanese pound", "exchangeRate": "0.120147", "inverseRate": "8.323157", "inverseDescription": "1 Sudanese pound = 8.323157 Kazakhstani Tenge"}, {"title": "1 KZT = 1.158656 SYP", "link": "http://www.floatrates.com/kzt/syp/", "description": "1 Kazakhstani Tenge = 1.158656 Syrian pound", "pubDate": null, "baseCurrency": "KZT", "baseName": "Kazakhstani Tenge", "targetCurrency": "SYP", "targetName": "Syrian pound", "exchangeRate": "1.158656", "inverseRate": "0.863069", "inverseDescription": "1 Syrian pound = 0.863069 Kazakhstani Tenge"}, {"title": "1 KZT = 0.015322 GHS", "link": "http://www.floatrates.com/kzt/ghs/", "description": "1 Kazakhstani Tenge = 0.015322 Ghanaian Cedi", "pubDate": null, "baseCurrency": "KZT", "baseName": "Kazakhstani Tenge", "targetCurrency": "GHS", "targetName": "Ghanaian Cedi", "exchangeRate": "0.015322", "inverseRate": "65.266087", "inverseDescription": "1 Ghanaian Cedi = 65.266087 Kazakhstani Tenge"}, {"title": "1 KZT = 0.262508 HTG", "link": "http://www.floatrates.com/kzt/htg/", "description": "1 Kazakhstani Tenge = 0.262508 Haitian gourde", "pubDate": null, "baseCurrency": "KZT", "baseName": "Kazakhstani Tenge", "targetCurrency": "HTG", "targetName": "Haitian gourde", "exchangeRate": "0.262508", "inverseRate": "3.809407", "inverseDescription": "1 Haitian gourde = 3.809407 Kazakhstani Tenge"}, {"title": "1 KZT = 17.264996 PYG", "link": "http://www.floatrates.com/kzt/pyg/", "description": "1 Kazakhstani Tenge = 17.264996 Paraguayan Guaran\u00ed", "pubDate": null, "baseCurrency": "KZT", "baseName": "Kazakhstani Tenge", "targetCurrency": "PYG", "targetName": "Paraguayan Guaran\u00ed", "exchangeRate": "17.264996", "inverseRate": "0.057921", "inverseDescription": "1 Paraguayan Guaran\u00ed = 0.057921 Kazakhstani Tenge"}, {"title": "1 KZT = 0.004285 ANG", "link": "http://www.floatrates.com/kzt/ang/", "description": "1 Kazakhstani Tenge = 0.004285 Neth. Antillean Guilder", "pubDate": null, "baseCurrency": "KZT", "baseName": "Kazakhstani Tenge", "targetCurrency": "ANG", "targetName": "Neth. Antillean Guilder", "exchangeRate": "0.004285", "inverseRate": "233.346010", "inverseDescription": "1 Neth. Antillean Guilder = 233.346010 Kazakhstani Tenge"}, {"title": "1 KZT = 23.552125 LAK", "link": "http://www.floatrates.com/kzt/lak/", "description": "1 Kazakhstani Tenge = 23.552125 Lao kip", "pubDate": null, "baseCurrency": "KZT", "baseName": "Kazakhstani Tenge", "targetCurrency": "LAK", "targetName": "Lao kip", "exchangeRate": "23.552125", "inverseRate": "0.042459", "inverseDescription": "1 Lao kip = 0.042459 Kazakhstani Tenge"}, {"title": "1 KZT = 1.947886 MWK", "link": "http://www.floatrates.com/kzt/mwk/", "description": "1 Kazakhstani Tenge = 1.947886 Malawian kwacha", "pubDate": null, "baseCurrency": "KZT", "baseName": "Kazakhstani Tenge", "targetCurrency": "MWK", "targetName": "Malawian kwacha", "exchangeRate": "1.947886", "inverseRate": "0.513377", "inverseDescription": "1 Malawian kwacha = 0.513377 Kazakhstani Tenge"}, {"title": "1 KZT = 0.038226 ZMW", "link": "http://www.floatrates.com/kzt/zmw/", "description": "1 Kazakhstani Tenge = 0.038226 Zambian kwacha", "pubDate": null, "baseCurrency": "KZT", "baseName": "Kazakhstani Tenge", "targetCurrency": "ZMW", "targetName": "Zambian kwacha", "exchangeRate": "0.038226", "inverseRate": "26.159911", "inverseDescription": "1 Zambian kwacha = 26.159911 Kazakhstani Tenge"}, {"title": "1 KZT = 1.275989 AOA", "link": "http://www.floatrates.com/kzt/aoa/", "description": "1 Kazakhstani Tenge = 1.275989 Angolan kwanza", "pubDate": null, "baseCurrency": "KZT", "baseName": "Kazakhstani Tenge", "targetCurrency": "AOA", "targetName": "Angolan kwanza", "exchangeRate": "1.275989", "inverseRate": "0.783706", "inverseDescription": "1 Angolan kwanza = 0.783706 Kazakhstani Tenge"}, {"title": "1 KZT = 3.925354 MMK", "link": "http://www.floatrates.com/kzt/mmk/", "description": "1 Kazakhstani Tenge = 3.925354 Myanma Kyat", "pubDate": null, "baseCurrency": "KZT", "baseName": "Kazakhstani Tenge", "targetCurrency": "MMK", "targetName": "Myanma Kyat", "exchangeRate": "3.925354", "inverseRate": "0.254754", "inverseDescription": "1 Myanma Kyat = 0.254754 Kazakhstani Tenge"}, {"title": "1 KZT = 0.007697 GEL", "link": "http://www.floatrates.com/kzt/gel/", "description": "1 Kazakhstani Tenge = 0.007697 Georgian lari", "pubDate": null, "baseCurrency": "KZT", "baseName": "Kazakhstani Tenge", "targetCurrency": "GEL", "targetName": "Georgian lari", "exchangeRate": "0.007697", "inverseRate": "129.922503", "inverseDescription": "1 Georgian lari = 129.922503 Kazakhstani Tenge"}, {"title": "1 KZT = 0.290876 ALL", "link": "http://www.floatrates.com/kzt/all/", "description": "1 Kazakhstani Tenge = 0.290876 Albanian lek", "pubDate": null, "baseCurrency": "KZT", "baseName": "Kazakhstani Tenge", "targetCurrency": "ALL", "targetName": "Albanian lek", "exchangeRate": "0.290876", "inverseRate": "3.437890", "inverseDescription": "1 Albanian lek = 3.437890 Kazakhstani Tenge"}, {"title": "1 KZT = 0.065372 HNL", "link": "http://www.floatrates.com/kzt/hnl/", "description": "1 Kazakhstani Tenge = 0.065372 Honduran Lempira", "pubDate": null, "baseCurrency": "KZT", "baseName": "Kazakhstani Tenge", "targetCurrency": "HNL", "targetName": "Honduran Lempira", "exchangeRate": "0.065372", "inverseRate": "15.297149", "inverseDescription": "1 Honduran Lempira = 15.297149 Kazakhstani Tenge"}, {"title": "1 KZT = 25.846947 SLL", "link": "http://www.floatrates.com/kzt/sll/", "description": "1 Kazakhstani Tenge = 25.846947 Sierra Leonean leone", "pubDate": null, "baseCurrency": "KZT", "baseName": "Kazakhstani Tenge", "targetCurrency": "SLL", "targetName": "Sierra Leonean leone", "exchangeRate": "25.846947", "inverseRate": "0.038689", "inverseDescription": "1 Sierra Leonean leone = 0.038689 Kazakhstani Tenge"}, {"title": "1 KZT = 0.038241 SZL", "link": "http://www.floatrates.com/kzt/szl/", "description": "1 Kazakhstani Tenge = 0.038241 Swazi lilangeni", "pubDate": null, "baseCurrency": "KZT", "baseName": "Kazakhstani Tenge", "targetCurrency": "SZL", "targetName": "Swazi lilangeni", "exchangeRate": "0.038241", "inverseRate": "26.149991", "inverseDescription": "1 Swazi lilangeni = 26.149991 Kazakhstani Tenge"}, {"title": "1 KZT = 0.038241 LSL", "link": "http://www.floatrates.com/kzt/lsl/", "description": "1 Kazakhstani Tenge = 0.038241 Lesotho loti", "pubDate": null, "baseCurrency": "KZT", "baseName": "Kazakhstani Tenge", "targetCurrency": "LSL", "targetName": "Lesotho loti", "exchangeRate": "0.038241", "inverseRate": "26.149991", "inverseDescription": "1 Lesotho loti = 26.149991 Kazakhstani Tenge"}, {"title": "1 KZT = 0.167169 MZN", "link": "http://www.floatrates.com/kzt/mzn/", "description": "1 Kazakhstani Tenge = 0.167169 Mozambican metical", "pubDate": null, "baseCurrency": "KZT", "baseName": "Kazakhstani Tenge", "targetCurrency": "MZN", "targetName": "Mozambican metical", "exchangeRate": "0.167169", "inverseRate": "5.981959", "inverseDescription": "1 Mozambican metical = 5.981959 Kazakhstani Tenge"}, {"title": "1 KZT = 0.813716 NGN", "link": "http://www.floatrates.com/kzt/ngn/", "description": "1 Kazakhstani Tenge = 0.813716 Nigerian Naira", "pubDate": null, "baseCurrency": "KZT", "baseName": "Kazakhstani Tenge", "targetCurrency": "NGN", "targetName": "Nigerian Naira", "exchangeRate": "0.813716", "inverseRate": "1.228931", "inverseDescription": "1 Nigerian Naira = 1.228931 Kazakhstani Tenge"}, {"title": "1 KZT = 0.040001 ERN", "link": "http://www.floatrates.com/kzt/ern/", "description": "1 Kazakhstani Tenge = 0.040001 Eritrean nakfa", "pubDate": null, "baseCurrency": "KZT", "baseName": "Kazakhstani Tenge", "targetCurrency": "ERN", "targetName": "Eritrean nakfa", "exchangeRate": "0.040001", "inverseRate": "24.999232", "inverseDescription": "1 Eritrean nakfa = 24.999232 Kazakhstani Tenge"}, {"title": "1 KZT = 0.099509 MRU", "link": "http://www.floatrates.com/kzt/mru/", "description": "1 Kazakhstani Tenge = 0.099509 Mauritanian ouguiya", "pubDate": null, "baseCurrency": "KZT", "baseName": "Kazakhstani Tenge", "targetCurrency": "MRU", "targetName": "Mauritanian ouguiya", "exchangeRate": "0.099509", "inverseRate": "10.049295", "inverseDescription": "1 Mauritanian ouguiya = 10.049295 Kazakhstani Tenge"}, {"title": "1 KZT = 0.006080 TOP", "link": "http://www.floatrates.com/kzt/top/", "description": "1 Kazakhstani Tenge = 0.006080 Tongan pa\u02bbanga", "pubDate": null, "baseCurrency": "KZT", "baseName": "Kazakhstani Tenge", "targetCurrency": "TOP", "targetName": "Tongan pa\u02bbanga", "exchangeRate": "0.006080", "inverseRate": "164.479077", "inverseDescription": "1 Tongan pa\u02bbanga = 164.479077 Kazakhstani Tenge"}, {"title": "1 KZT = 0.021262 MOP", "link": "http://www.floatrates.com/kzt/mop/", "description": "1 Kazakhstani Tenge = 0.021262 Macanese pataca", "pubDate": null, "baseCurrency": "KZT", "baseName": "Kazakhstani Tenge", "targetCurrency": "MOP", "targetName": "Macanese pataca", "exchangeRate": "0.021262", "inverseRate": "47.032286", "inverseDescription": "1 Macanese pataca = 47.032286 Kazakhstani Tenge"}, {"title": "1 KZT = 0.159219 ARS", "link": "http://www.floatrates.com/kzt/ars/", "description": "1 Kazakhstani Tenge = 0.159219 Argentine Peso", "pubDate": null, "baseCurrency": "KZT", "baseName": "Kazakhstani Tenge", "targetCurrency": "ARS", "targetName": "Argentine Peso", "exchangeRate": "0.159219", "inverseRate": "6.280648", "inverseDescription": "1 Argentine Peso = 6.280648 Kazakhstani Tenge"}, {"title": "1 KZT = 0.140590 DOP", "link": "http://www.floatrates.com/kzt/dop/", "description": "1 Kazakhstani Tenge = 0.140590 Dominican Peso", "pubDate": null, "baseCurrency": "KZT", "baseName": "Kazakhstani Tenge", "targetCurrency": "DOP", "targetName": "Dominican Peso", "exchangeRate": "0.140590", "inverseRate": "7.112877", "inverseDescription": "1 Dominican Peso = 7.112877 Kazakhstani Tenge"}, {"title": "1 KZT = 8.775111 COP", "link": "http://www.floatrates.com/kzt/cop/", "description": "1 Kazakhstani Tenge = 8.775111 Colombian Peso", "pubDate": null, "baseCurrency": "KZT", "baseName": "Kazakhstani Tenge", "targetCurrency": "COP", "targetName": "Colombian Peso", "exchangeRate": "8.775111", "inverseRate": "0.113959", "inverseDescription": "1 Colombian Peso = 0.113959 Kazakhstani Tenge"}, {"title": "1 KZT = 0.002653 CUP", "link": "http://www.floatrates.com/kzt/cup/", "description": "1 Kazakhstani Tenge = 0.002653 Cuban peso", "pubDate": null, "baseCurrency": "KZT", "baseName": "Kazakhstani Tenge", "targetCurrency": "CUP", "targetName": "Cuban peso", "exchangeRate": "0.002653", "inverseRate": "376.893190", "inverseDescription": "1 Cuban peso = 376.893190 Kazakhstani Tenge"}, {"title": "1 KZT = 0.098843 UYU", "link": "http://www.floatrates.com/kzt/uyu/", "description": "1 Kazakhstani Tenge = 0.098843 Uruguayan Peso", "pubDate": null, "baseCurrency": "KZT", "baseName": "Kazakhstani Tenge", "targetCurrency": "UYU", "targetName": "Uruguayan Peso", "exchangeRate": "0.098843", "inverseRate": "10.117081", "inverseDescription": "1 Uruguayan Peso = 10.117081 Kazakhstani Tenge"}, {"title": "1 KZT = 0.028368 BWP", "link": "http://www.floatrates.com/kzt/bwp/", "description": "1 Kazakhstani Tenge = 0.028368 Botswana Pula", "pubDate": null, "baseCurrency": "KZT", "baseName": "Kazakhstani Tenge", "targetCurrency": "BWP", "targetName": "Botswana Pula", "exchangeRate": "0.028368", "inverseRate": "35.251158", "inverseDescription": "1 Botswana Pula = 35.251158 Kazakhstani Tenge"}, {"title": "1 KZT = 0.020472 GTQ", "link": "http://www.floatrates.com/kzt/gtq/", "description": "1 Kazakhstani Tenge = 0.020472 Guatemalan Quetzal", "pubDate": null, "baseCurrency": "KZT", "baseName": "Kazakhstani Tenge", "targetCurrency": "GTQ", "targetName": "Guatemalan Quetzal", "exchangeRate": "0.020472", "inverseRate": "48.847707", "inverseDescription": "1 Guatemalan Quetzal = 48.847707 Kazakhstani Tenge"}, {"title": "1 KZT = 112.961297 IRR", "link": "http://www.floatrates.com/kzt/irr/", "description": "1 Kazakhstani Tenge = 112.961297 Iranian rial", "pubDate": null, "baseCurrency": "KZT", "baseName": "Kazakhstani Tenge", "targetCurrency": "IRR", "targetName": "Iranian rial", "exchangeRate": "112.961297", "inverseRate": "0.008853", "inverseDescription": "1 Iranian rial = 0.008853 Kazakhstani Tenge"}, {"title": "1 KZT = 0.661524 YER", "link": "http://www.floatrates.com/kzt/yer/", "description": "1 Kazakhstani Tenge = 0.661524 Yemeni rial", "pubDate": null, "baseCurrency": "KZT", "baseName": "Kazakhstani Tenge", "targetCurrency": "YER", "targetName": "Yemeni rial", "exchangeRate": "0.661524", "inverseRate": "1.511660", "inverseDescription": "1 Yemeni rial = 1.511660 Kazakhstani Tenge"}, {"title": "1 KZT = 0.009716 QAR", "link": "http://www.floatrates.com/kzt/qar/", "description": "1 Kazakhstani Tenge = 0.009716 Qatari Rial", "pubDate": null, "baseCurrency": "KZT", "baseName": "Kazakhstani Tenge", "targetCurrency": "QAR", "targetName": "Qatari Rial", "exchangeRate": "0.009716", "inverseRate": "102.923427", "inverseDescription": "1 Qatari Rial = 102.923427 Kazakhstani Tenge"}, {"title": "1 KZT = 0.001019 OMR", "link": "http://www.floatrates.com/kzt/omr/", "description": "1 Kazakhstani Tenge = 0.001019 Omani Rial", "pubDate": null, "baseCurrency": "KZT", "baseName": "Kazakhstani Tenge", "targetCurrency": "OMR", "targetName": "Omani Rial", "exchangeRate": "0.001019", "inverseRate": "981.219873", "inverseDescription": "1 Omani Rial = 981.219873 Kazakhstani Tenge"}, {"title": "1 KZT = 0.009936 SAR", "link": "http://www.floatrates.com/kzt/sar/", "description": "1 Kazakhstani Tenge = 0.009936 Saudi Riyal", "pubDate": null, "baseCurrency": "KZT", "baseName": "Kazakhstani Tenge", "targetCurrency": "SAR", "targetName": "Saudi Riyal", "exchangeRate": "0.009936", "inverseRate": "100.643532", "inverseDescription": "1 Saudi Riyal = 100.643532 Kazakhstani Tenge"}, {"title": "1 KZT = 10.815783 KHR", "link": "http://www.floatrates.com/kzt/khr/", "description": "1 Kazakhstani Tenge = 10.815783 Cambodian riel", "pubDate": null, "baseCurrency": "KZT", "baseName": "Kazakhstani Tenge", "targetCurrency": "KHR", "targetName": "Cambodian riel", "exchangeRate": "10.815783", "inverseRate": "0.092457", "inverseDescription": "1 Cambodian riel = 0.092457 Kazakhstani Tenge"}, {"title": "1 KZT = 0.481482 LKR", "link": "http://www.floatrates.com/kzt/lkr/", "description": "1 Kazakhstani Tenge = 0.481482 Sri Lanka Rupee", "pubDate": null, "baseCurrency": "KZT", "baseName": "Kazakhstani Tenge", "targetCurrency": "LKR", "targetName": "Sri Lanka Rupee", "exchangeRate": "0.481482", "inverseRate": "2.076920", "inverseDescription": "1 Sri Lanka Rupee = 2.076920 Kazakhstani Tenge"}, {"title": "1 KZT = 0.041027 MVR", "link": "http://www.floatrates.com/kzt/mvr/", "description": "1 Kazakhstani Tenge = 0.041027 Maldivian rufiyaa", "pubDate": null, "baseCurrency": "KZT", "baseName": "Kazakhstani Tenge", "targetCurrency": "MVR", "targetName": "Maldivian rufiyaa", "exchangeRate": "0.041027", "inverseRate": "24.374252", "inverseDescription": "1 Maldivian rufiyaa = 24.374252 Kazakhstani Tenge"}, {"title": "1 KZT = 0.096787 MUR", "link": "http://www.floatrates.com/kzt/mur/", "description": "1 Kazakhstani Tenge = 0.096787 Mauritian Rupee", "pubDate": null, "baseCurrency": "KZT", "baseName": "Kazakhstani Tenge", "targetCurrency": "MUR", "targetName": "Mauritian Rupee", "exchangeRate": "0.096787", "inverseRate": "10.331931", "inverseDescription": "1 Mauritian Rupee = 10.331931 Kazakhstani Tenge"}, {"title": "1 KZT = 0.300833 NPR", "link": "http://www.floatrates.com/kzt/npr/", "description": "1 Kazakhstani Tenge = 0.300833 Nepalese Rupee", "pubDate": null, "baseCurrency": "KZT", "baseName": "Kazakhstani Tenge", "targetCurrency": "NPR", "targetName": "Nepalese Rupee", "exchangeRate": "0.300833", "inverseRate": "3.324104", "inverseDescription": "1 Nepalese Rupee = 3.324104 Kazakhstani Tenge"}, {"title": "1 KZT = 0.410507 PKR", "link": "http://www.floatrates.com/kzt/pkr/", "description": "1 Kazakhstani Tenge = 0.410507 Pakistani Rupee", "pubDate": null, "baseCurrency": "KZT", "baseName": "Kazakhstani Tenge", "targetCurrency": "PKR", "targetName": "Pakistani Rupee", "exchangeRate": "0.410507", "inverseRate": "2.436015", "inverseDescription": "1 Pakistani Rupee = 2.436015 Kazakhstani Tenge"}, {"title": "1 KZT = 0.036352 SCR", "link": "http://www.floatrates.com/kzt/scr/", "description": "1 Kazakhstani Tenge = 0.036352 Seychelles rupee", "pubDate": null, "baseCurrency": "KZT", "baseName": "Kazakhstani Tenge", "targetCurrency": "SCR", "targetName": "Seychelles rupee", "exchangeRate": "0.036352", "inverseRate": "27.509076", "inverseDescription": "1 Seychelles rupee = 27.509076 Kazakhstani Tenge"}, {"title": "1 KZT = 0.008799 PEN", "link": "http://www.floatrates.com/kzt/pen/", "description": "1 Kazakhstani Tenge = 0.008799 Peruvian Nuevo Sol", "pubDate": null, "baseCurrency": "KZT", "baseName": "Kazakhstani Tenge", "targetCurrency": "PEN", "targetName": "Peruvian Nuevo Sol", "exchangeRate": "0.008799", "inverseRate": "113.654369", "inverseDescription": "1 Peruvian Nuevo Sol = 113.654369 Kazakhstani Tenge"}, {"title": "1 KZT = 0.269095 KES", "link": "http://www.floatrates.com/kzt/kes/", "description": "1 Kazakhstani Tenge = 0.269095 Kenyan shilling", "pubDate": null, "baseCurrency": "KZT", "baseName": "Kazakhstani Tenge", "targetCurrency": "KES", "targetName": "Kenyan shilling", "exchangeRate": "0.269095", "inverseRate": "3.716156", "inverseDescription": "1 Kenyan shilling = 3.716156 Kazakhstani Tenge"}, {"title": "1 KZT = 1.534995 SOS", "link": "http://www.floatrates.com/kzt/sos/", "description": "1 Kazakhstani Tenge = 1.534995 Somali shilling", "pubDate": null, "baseCurrency": "KZT", "baseName": "Kazakhstani Tenge", "targetCurrency": "SOS", "targetName": "Somali shilling", "exchangeRate": "1.534995", "inverseRate": "0.651468", "inverseDescription": "1 Somali shilling = 0.651468 Kazakhstani Tenge"}, {"title": "1 KZT = 6.120406 TZS", "link": "http://www.floatrates.com/kzt/tzs/", "description": "1 Kazakhstani Tenge = 6.120406 Tanzanian shilling", "pubDate": null, "baseCurrency": "KZT", "baseName": "Kazakhstani Tenge", "targetCurrency": "TZS", "targetName": "Tanzanian shilling", "exchangeRate": "6.120406", "inverseRate": "0.163388", "inverseDescription": "1 Tanzanian shilling = 0.163388 Kazakhstani Tenge"}, {"title": "1 KZT = 9.739429 UGX", "link": "http://www.floatrates.com/kzt/ugx/", "description": "1 Kazakhstani Tenge = 9.739429 Ugandan shilling", "pubDate": null, "baseCurrency": "KZT", "baseName": "Kazakhstani Tenge", "targetCurrency": "UGX", "targetName": "Ugandan shilling", "exchangeRate": "9.739429", "inverseRate": "0.102675", "inverseDescription": "1 Ugandan shilling = 0.102675 Kazakhstani Tenge"}, {"title": "1 KZT = 0.226715 BDT", "link": "http://www.floatrates.com/kzt/bdt/", "description": "1 Kazakhstani Tenge = 0.226715 Bangladeshi taka", "pubDate": null, "baseCurrency": "KZT", "baseName": "Kazakhstani Tenge", "targetCurrency": "BDT", "targetName": "Bangladeshi taka", "exchangeRate": "0.226715", "inverseRate": "4.410825", "inverseDescription": "1 Bangladeshi taka = 4.410825 Kazakhstani Tenge"}, {"title": "1 KZT = 0.006998 WST", "link": "http://www.floatrates.com/kzt/wst/", "description": "1 Kazakhstani Tenge = 0.006998 Samoan tala", "pubDate": null, "baseCurrency": "KZT", "baseName": "Kazakhstani Tenge", "targetCurrency": "WST", "targetName": "Samoan tala", "exchangeRate": "0.006998", "inverseRate": "142.902358", "inverseDescription": "1 Samoan tala = 142.902358 Kazakhstani Tenge"}, {"title": "1 KZT = 7.283461 MNT", "link": "http://www.floatrates.com/kzt/mnt/", "description": "1 Kazakhstani Tenge = 7.283461 Mongolian togrog", "pubDate": null, "baseCurrency": "KZT", "baseName": "Kazakhstani Tenge", "targetCurrency": "MNT", "targetName": "Mongolian togrog", "exchangeRate": "7.283461", "inverseRate": "0.137297", "inverseDescription": "1 Mongolian togrog = 0.137297 Kazakhstani Tenge"}, {"title": "1 KZT = 0.309915 VUV", "link": "http://www.floatrates.com/kzt/vuv/", "description": "1 Kazakhstani Tenge = 0.309915 Vanuatu vatu", "pubDate": null, "baseCurrency": "KZT", "baseName": "Kazakhstani Tenge", "targetCurrency": "VUV", "targetName": "Vanuatu vatu", "exchangeRate": "0.309915", "inverseRate": "3.226687", "inverseDescription": "1 Vanuatu vatu = 3.226687 Kazakhstani Tenge"}, {"title": "1 KZT = 0.004663 BAM", "link": "http://www.floatrates.com/kzt/bam/", "description": "1 Kazakhstani Tenge = 0.004663 Bosnia and Herzegovina convertible mark", "pubDate": null, "baseCurrency": "KZT", "baseName": "Kazakhstani Tenge", "targetCurrency": "BAM", "targetName": "Bosnia and Herzegovina convertible mark", "exchangeRate": "0.004663", "inverseRate": "214.447781", "inverseDescription": "1 Bosnia and Herzegovina convertible mark = 214.447781 Kazakhstani Tenge"}, {"title": "1 KZT = 0.096661 MRO", "link": "http://www.floatrates.com/kzt/mro/", "description": "1 Kazakhstani Tenge = 0.096661 Mauritanian Ouguiya", "pubDate": null, "baseCurrency": "KZT", "baseName": "Kazakhstani Tenge", "targetCurrency": "MRO", "targetName": "Mauritanian Ouguiya", "exchangeRate": "0.096661", "inverseRate": "10.345425", "inverseDescription": "1 Mauritanian Ouguiya = 10.345425 Kazakhstani Tenge"}]}}