{
    "channel": {
        "title": "XML Historical Foreign Exchange Rates for Kuwaiti Dinar (KWD) (5 May 2023)",
        "link": "http://www.floatrates.com/currency/kwd/",
        "xmlLink": "http://www.floatrates.com/daily/kwd.xml",
        "description": "XML historical foreign exchange rates for Kuwaiti Dinar (KWD) from the Float Rates. Published at 5 May 2023.",
        "language": "en",
        "baseCurrency": "KWD",
        "pubDate": "Fri, 5 May 2023",
        "lastBuildDate": "Fri, 5 May 2023",
        "item": [
            {
                "title": "1 KWD = 2.968666 EUR",
                "link": "http://www.floatrates.com/kwd/eur/",
                "description": "1 Kuwaiti Dinar = 2.968666 Euro",
                "pubDate": null,
                "baseCurrency": "KWD",
                "baseName": "Kuwaiti Dinar",
                "targetCurrency": "EUR",
                "targetName": "Euro",
                "exchangeRate": "2.968666",
                "inverseRate": "0.336852",
                "inverseDescription": "1 Euro = 0.336852 Kuwaiti Dinar"
            },
            {
                "title": "1 KWD = 3.273676 USD",
                "link": "http://www.floatrates.com/kwd/usd/",
                "description": "1 Kuwaiti Dinar = 3.273676 U.S. Dollar",
                "pubDate": null,
                "baseCurrency": "KWD",
                "baseName": "Kuwaiti Dinar",
                "targetCurrency": "USD",
                "targetName": "U.S. Dollar",
                "exchangeRate": "3.273676",
                "inverseRate": "0.305467",
                "inverseDescription": "1 U.S. Dollar = 0.305467 Kuwaiti Dinar"
            },
            {
                "title": "1 KWD = 4.404992 CAD",
                "link": "http://www.floatrates.com/kwd/cad/",
                "description": "1 Kuwaiti Dinar = 4.404992 Canadian Dollar",
                "pubDate": null,
                "baseCurrency": "KWD",
                "baseName": "Kuwaiti Dinar",
                "targetCurrency": "CAD",
                "targetName": "Canadian Dollar",
                "exchangeRate": "4.404992",
                "inverseRate": "0.227015",
                "inverseDescription": "1 Canadian Dollar = 0.227015 Kuwaiti Dinar"
            },
            {
                "title": "1 KWD = 2.598895 GBP",
                "link": "http://www.floatrates.com/kwd/gbp/",
                "description": "1 Kuwaiti Dinar = 2.598895 U.K. Pound Sterling",
                "pubDate": null,
                "baseCurrency": "KWD",
                "baseName": "Kuwaiti Dinar",
                "targetCurrency": "GBP",
                "targetName": "U.K. Pound Sterling",
                "exchangeRate": "2.598895",
                "inverseRate": "0.384779",
                "inverseDescription": "1 U.K. Pound Sterling = 0.384779 Kuwaiti Dinar"
            },
            {
                "title": "1 KWD = 2.609767 GIP",
                "link": "http://www.floatrates.com/kwd/gip/",
                "description": "1 Kuwaiti Dinar = 2.609767 Gibraltar pound",
                "pubDate": null,
                "baseCurrency": "KWD",
                "baseName": "Kuwaiti Dinar",
                "targetCurrency": "GIP",
                "targetName": "Gibraltar pound",
                "exchangeRate": "2.609767",
                "inverseRate": "0.383176",
                "inverseDescription": "1 Gibraltar pound = 0.383176 Kuwaiti Dinar"
            },
            {
                "title": "1 KWD = 2.910211 CHF",
                "link": "http://www.floatrates.com/kwd/chf/",
                "description": "1 Kuwaiti Dinar = 2.910211 Swiss Franc",
                "pubDate": null,
                "baseCurrency": "KWD",
                "baseName": "Kuwaiti Dinar",
                "targetCurrency": "CHF",
                "targetName": "Swiss Franc",
                "exchangeRate": "2.910211",
                "inverseRate": "0.343618",
                "inverseDescription": "1 Swiss Franc = 0.343618 Kuwaiti Dinar"
            },
            {
                "title": "1 KWD = 22.136596 DKK",
                "link": "http://www.floatrates.com/kwd/dkk/",
                "description": "1 Kuwaiti Dinar = 22.136596 Danish Krone",
                "pubDate": null,
                "baseCurrency": "KWD",
                "baseName": "Kuwaiti Dinar",
                "targetCurrency": "DKK",
                "targetName": "Danish Krone",
                "exchangeRate": "22.136596",
                "inverseRate": "0.045174",
                "inverseDescription": "1 Danish Krone = 0.045174 Kuwaiti Dinar"
            },
            {
                "title": "1 KWD = 33.357141 SEK",
                "link": "http://www.floatrates.com/kwd/sek/",
                "description": "1 Kuwaiti Dinar = 33.357141 Swedish Krona",
                "pubDate": null,
                "baseCurrency": "KWD",
                "baseName": "Kuwaiti Dinar",
                "targetCurrency": "SEK",
                "targetName": "Swedish Krona",
                "exchangeRate": "33.357141",
                "inverseRate": "0.029979",
                "inverseDescription": "1 Swedish Krona = 0.029979 Kuwaiti Dinar"
            },
            {
                "title": "1 KWD = 34.701006 NOK",
                "link": "http://www.floatrates.com/kwd/nok/",
                "description": "1 Kuwaiti Dinar = 34.701006 Norwegian Krone",
                "pubDate": null,
                "baseCurrency": "KWD",
                "baseName": "Kuwaiti Dinar",
                "targetCurrency": "NOK",
                "targetName": "Norwegian Krone",
                "exchangeRate": "34.701006",
                "inverseRate": "0.028818",
                "inverseDescription": "1 Norwegian Krone = 0.028818 Kuwaiti Dinar"
            },
            {
                "title": "1 KWD = 12.275946 SAR",
                "link": "http://www.floatrates.com/kwd/sar/",
                "description": "1 Kuwaiti Dinar = 12.275946 Saudi Riyal",
                "pubDate": null,
                "baseCurrency": "KWD",
                "baseName": "Kuwaiti Dinar",
                "targetCurrency": "SAR",
                "targetName": "Saudi Riyal",
                "exchangeRate": "12.275946",
                "inverseRate": "0.081460",
                "inverseDescription": "1 Saudi Riyal = 0.081460 Kuwaiti Dinar"
            },
            {
                "title": "1 KWD = 1.000000 KWD",
                "link": "http://www.floatrates.com/kwd/kwd/",
                "description": "1 Kuwaiti Dinar = 1.000000 Kuwaiti Dinar",
                "pubDate": null,
                "baseCurrency": "KWD",
                "baseName": "Kuwaiti Dinar",
                "targetCurrency": "KWD",
                "targetName": "Kuwaiti Dinar",
                "exchangeRate": "1.000000",
                "inverseRate": "1.000000",
                "inverseDescription": "1 Kuwaiti Dinar = 1.000000 Kuwaiti Dinar"
            },
            {
                "title": "1 KWD = 12.007217 AED",
                "link": "http://www.floatrates.com/kwd/aed/",
                "description": "1 Kuwaiti Dinar = 12.007217 U.A.E Dirham",
                "pubDate": null,
                "baseCurrency": "KWD",
                "baseName": "Kuwaiti Dinar",
                "targetCurrency": "AED",
                "targetName": "U.A.E Dirham",
                "exchangeRate": "12.007217",
                "inverseRate": "0.083283",
                "inverseDescription": "1 U.A.E Dirham = 0.083283 Kuwaiti Dinar"
            },
            {
                "title": "1 KWD = 11.943397 QAR",
                "link": "http://www.floatrates.com/kwd/qar/",
                "description": "1 Kuwaiti Dinar = 11.943397 Qatari Rial",
                "pubDate": null,
                "baseCurrency": "KWD",
                "baseName": "Kuwaiti Dinar",
                "targetCurrency": "QAR",
                "targetName": "Qatari Rial",
                "exchangeRate": "11.943397",
                "inverseRate": "0.083728",
                "inverseDescription": "1 Qatari Rial = 0.083728 Kuwaiti Dinar"
            },
            {
                "title": "1 KWD = 1.229919 BHD",
                "link": "http://www.floatrates.com/kwd/bhd/",
                "description": "1 Kuwaiti Dinar = 1.229919 Bahrain Dinar",
                "pubDate": null,
                "baseCurrency": "KWD",
                "baseName": "Kuwaiti Dinar",
                "targetCurrency": "BHD",
                "targetName": "Bahrain Dinar",
                "exchangeRate": "1.229919",
                "inverseRate": "0.813062",
                "inverseDescription": "1 Bahrain Dinar = 0.813062 Kuwaiti Dinar"
            },
            {
                "title": "1 KWD = 440.041017 JPY",
                "link": "http://www.floatrates.com/kwd/jpy/",
                "description": "1 Kuwaiti Dinar = 440.041017 Japanese Yen",
                "pubDate": null,
                "baseCurrency": "KWD",
                "baseName": "Kuwaiti Dinar",
                "targetCurrency": "JPY",
                "targetName": "Japanese Yen",
                "exchangeRate": "440.041017",
                "inverseRate": "0.002273",
                "inverseDescription": "1 Japanese Yen = 0.002273 Kuwaiti Dinar"
            },
            {
                "title": "1 KWD = 442.395535 DZD",
                "link": "http://www.floatrates.com/kwd/dzd/",
                "description": "1 Kuwaiti Dinar = 442.395535 Algerian Dinar",
                "pubDate": null,
                "baseCurrency": "KWD",
                "baseName": "Kuwaiti Dinar",
                "targetCurrency": "DZD",
                "targetName": "Algerian Dinar",
                "exchangeRate": "442.395535",
                "inverseRate": "0.002260",
                "inverseDescription": "1 Algerian Dinar = 0.002260 Kuwaiti Dinar"
            },
            {
                "title": "1 KWD = 9.953151 TND",
                "link": "http://www.floatrates.com/kwd/tnd/",
                "description": "1 Kuwaiti Dinar = 9.953151 Tunisian Dinar",
                "pubDate": null,
                "baseCurrency": "KWD",
                "baseName": "Kuwaiti Dinar",
                "targetCurrency": "TND",
                "targetName": "Tunisian Dinar",
                "exchangeRate": "9.953151",
                "inverseRate": "0.100471",
                "inverseDescription": "1 Tunisian Dinar = 0.100471 Kuwaiti Dinar"
            },
            {
                "title": "1 KWD = 15.593551 LYD",
                "link": "http://www.floatrates.com/kwd/lyd/",
                "description": "1 Kuwaiti Dinar = 15.593551 Libyan Dinar",
                "pubDate": null,
                "baseCurrency": "KWD",
                "baseName": "Kuwaiti Dinar",
                "targetCurrency": "LYD",
                "targetName": "Libyan Dinar",
                "exchangeRate": "15.593551",
                "inverseRate": "0.064129",
                "inverseDescription": "1 Libyan Dinar = 0.064129 Kuwaiti Dinar"
            },
            {
                "title": "1 KWD = 112.334805 MRO",
                "link": "http://www.floatrates.com/kwd/mro/",
                "description": "1 Kuwaiti Dinar = 112.334805 Mauritanian Ouguiya",
                "pubDate": null,
                "baseCurrency": "KWD",
                "baseName": "Kuwaiti Dinar",
                "targetCurrency": "MRO",
                "targetName": "Mauritanian Ouguiya",
                "exchangeRate": "112.334805",
                "inverseRate": "0.008902",
                "inverseDescription": "1 Mauritanian Ouguiya = 0.008902 Kuwaiti Dinar"
            },
            {
                "title": "1 KWD = 1.255866 OMR",
                "link": "http://www.floatrates.com/kwd/omr/",
                "description": "1 Kuwaiti Dinar = 1.255866 Omani Rial",
                "pubDate": null,
                "baseCurrency": "KWD",
                "baseName": "Kuwaiti Dinar",
                "targetCurrency": "OMR",
                "targetName": "Omani Rial",
                "exchangeRate": "1.255866",
                "inverseRate": "0.796263",
                "inverseDescription": "1 Omani Rial = 0.796263 Kuwaiti Dinar"
            },
            {
                "title": "1 KWD = 16.269265 BRL",
                "link": "http://www.floatrates.com/kwd/brl/",
                "description": "1 Kuwaiti Dinar = 16.269265 Brazilian Real",
                "pubDate": null,
                "baseCurrency": "KWD",
                "baseName": "Kuwaiti Dinar",
                "targetCurrency": "BRL",
                "targetName": "Brazilian Real",
                "exchangeRate": "16.269265",
                "inverseRate": "0.061466",
                "inverseDescription": "1 Brazilian Real = 0.061466 Kuwaiti Dinar"
            },
            {
                "title": "1 KWD = 259.067144 RUB",
                "link": "http://www.floatrates.com/kwd/rub/",
                "description": "1 Kuwaiti Dinar = 259.067144 Russian Rouble",
                "pubDate": null,
                "baseCurrency": "KWD",
                "baseName": "Kuwaiti Dinar",
                "targetCurrency": "RUB",
                "targetName": "Russian Rouble",
                "exchangeRate": "259.067144",
                "inverseRate": "0.003860",
                "inverseDescription": "1 Russian Rouble = 0.003860 Kuwaiti Dinar"
            },
            {
                "title": "1 KWD = 267.621329 INR",
                "link": "http://www.floatrates.com/kwd/inr/",
                "description": "1 Kuwaiti Dinar = 267.621329 Indian Rupee",
                "pubDate": null,
                "baseCurrency": "KWD",
                "baseName": "Kuwaiti Dinar",
                "targetCurrency": "INR",
                "targetName": "Indian Rupee",
                "exchangeRate": "267.621329",
                "inverseRate": "0.003737",
                "inverseDescription": "1 Indian Rupee = 0.003737 Kuwaiti Dinar"
            },
            {
                "title": "1 KWD = 22.628429 CNY",
                "link": "http://www.floatrates.com/kwd/cny/",
                "description": "1 Kuwaiti Dinar = 22.628429 Chinese Yuan",
                "pubDate": null,
                "baseCurrency": "KWD",
                "baseName": "Kuwaiti Dinar",
                "targetCurrency": "CNY",
                "targetName": "Chinese Yuan",
                "exchangeRate": "22.628429",
                "inverseRate": "0.044192",
                "inverseDescription": "1 Chinese Yuan = 0.044192 Kuwaiti Dinar"
            },
            {
                "title": "1 KWD = 4.861406 AUD",
                "link": "http://www.floatrates.com/kwd/aud/",
                "description": "1 Kuwaiti Dinar = 4.861406 Australian Dollar",
                "pubDate": null,
                "baseCurrency": "KWD",
                "baseName": "Kuwaiti Dinar",
                "targetCurrency": "AUD",
                "targetName": "Australian Dollar",
                "exchangeRate": "4.861406",
                "inverseRate": "0.205702",
                "inverseDescription": "1 Australian Dollar = 0.205702 Kuwaiti Dinar"
            },
            {
                "title": "1 KWD = 60.220889 ZAR",
                "link": "http://www.floatrates.com/kwd/zar/",
                "description": "1 Kuwaiti Dinar = 60.220889 South African Rand",
                "pubDate": null,
                "baseCurrency": "KWD",
                "baseName": "Kuwaiti Dinar",
                "targetCurrency": "ZAR",
                "targetName": "South African Rand",
                "exchangeRate": "60.220889",
                "inverseRate": "0.016606",
                "inverseDescription": "1 South African Rand = 0.016606 Kuwaiti Dinar"
            },
            {
                "title": "1 KWD = 63.809603 TRY",
                "link": "http://www.floatrates.com/kwd/try/",
                "description": "1 Kuwaiti Dinar = 63.809603 Turkish Lira",
                "pubDate": null,
                "baseCurrency": "KWD",
                "baseName": "Kuwaiti Dinar",
                "targetCurrency": "TRY",
                "targetName": "Turkish Lira",
                "exchangeRate": "63.809603",
                "inverseRate": "0.015672",
                "inverseDescription": "1 Turkish Lira = 0.015672 Kuwaiti Dinar"
            },
            {
                "title": "1 KWD = 101.214980 EGP",
                "link": "http://www.floatrates.com/kwd/egp/",
                "description": "1 Kuwaiti Dinar = 101.214980 Egyptian Pound",
                "pubDate": null,
                "baseCurrency": "KWD",
                "baseName": "Kuwaiti Dinar",
                "targetCurrency": "EGP",
                "targetName": "Egyptian Pound",
                "exchangeRate": "101.214980",
                "inverseRate": "0.009880",
                "inverseDescription": "1 Egyptian Pound = 0.009880 Kuwaiti Dinar"
            },
            {
                "title": "1 KWD = 2.318802 JOD",
                "link": "http://www.floatrates.com/kwd/jod/",
                "description": "1 Kuwaiti Dinar = 2.318802 Jordanian Dinar",
                "pubDate": null,
                "baseCurrency": "KWD",
                "baseName": "Kuwaiti Dinar",
                "targetCurrency": "JOD",
                "targetName": "Jordanian Dinar",
                "exchangeRate": "2.318802",
                "inverseRate": "0.431257",
                "inverseDescription": "1 Jordanian Dinar = 0.431257 Kuwaiti Dinar"
            },
            {
                "title": "1 KWD = 1,949.364349 XOF",
                "link": "http://www.floatrates.com/kwd/xof/",
                "description": "1 Kuwaiti Dinar = 1,949.364349 West African CFA Franc",
                "pubDate": null,
                "baseCurrency": "KWD",
                "baseName": "Kuwaiti Dinar",
                "targetCurrency": "XOF",
                "targetName": "West African CFA Franc",
                "exchangeRate": "1,949.364349",
                "inverseRate": "0.000513",
                "inverseDescription": "1 West African CFA Franc = 0.000513 Kuwaiti Dinar"
            },
            {
                "title": "1 KWD = 32.918031 MAD",
                "link": "http://www.floatrates.com/kwd/mad/",
                "description": "1 Kuwaiti Dinar = 32.918031 Moroccan Dirham",
                "pubDate": null,
                "baseCurrency": "KWD",
                "baseName": "Kuwaiti Dinar",
                "targetCurrency": "MAD",
                "targetName": "Moroccan Dirham",
                "exchangeRate": "32.918031",
                "inverseRate": "0.030378",
                "inverseDescription": "1 Moroccan Dirham = 0.030378 Kuwaiti Dinar"
            },
            {
                "title": "1 KWD = 4,321.637763 KRW",
                "link": "http://www.floatrates.com/kwd/krw/",
                "description": "1 Kuwaiti Dinar = 4,321.637763 South Korean Won",
                "pubDate": null,
                "baseCurrency": "KWD",
                "baseName": "Kuwaiti Dinar",
                "targetCurrency": "KRW",
                "targetName": "South Korean Won",
                "exchangeRate": "4,321.637763",
                "inverseRate": "0.000231",
                "inverseDescription": "1 South Korean Won = 0.000231 Kuwaiti Dinar"
            },
            {
                "title": "1 KWD = 4.338980 SGD",
                "link": "http://www.floatrates.com/kwd/sgd/",
                "description": "1 Kuwaiti Dinar = 4.338980 Singapore Dollar",
                "pubDate": null,
                "baseCurrency": "KWD",
                "baseName": "Kuwaiti Dinar",
                "targetCurrency": "SGD",
                "targetName": "Singapore Dollar",
                "exchangeRate": "4.338980",
                "inverseRate": "0.230469",
                "inverseDescription": "1 Singapore Dollar = 0.230469 Kuwaiti Dinar"
            },
            {
                "title": "1 KWD = 100.372701 TWD",
                "link": "http://www.floatrates.com/kwd/twd/",
                "description": "1 Kuwaiti Dinar = 100.372701 New Taiwan Dollar",
                "pubDate": null,
                "baseCurrency": "KWD",
                "baseName": "Kuwaiti Dinar",
                "targetCurrency": "TWD",
                "targetName": "New Taiwan Dollar",
                "exchangeRate": "100.372701",
                "inverseRate": "0.009963",
                "inverseDescription": "1 New Taiwan Dollar  = 0.009963 Kuwaiti Dinar"
            },
            {
                "title": "1 KWD = 14.531868 MYR",
                "link": "http://www.floatrates.com/kwd/myr/",
                "description": "1 Kuwaiti Dinar = 14.531868 Malaysian Ringgit",
                "pubDate": null,
                "baseCurrency": "KWD",
                "baseName": "Kuwaiti Dinar",
                "targetCurrency": "MYR",
                "targetName": "Malaysian Ringgit",
                "exchangeRate": "14.531868",
                "inverseRate": "0.068814",
                "inverseDescription": "1 Malaysian Ringgit = 0.068814 Kuwaiti Dinar"
            },
            {
                "title": "1 KWD = 5.197278 NZD",
                "link": "http://www.floatrates.com/kwd/nzd/",
                "description": "1 Kuwaiti Dinar = 5.197278 New Zealand Dollar",
                "pubDate": null,
                "baseCurrency": "KWD",
                "baseName": "Kuwaiti Dinar",
                "targetCurrency": "NZD",
                "targetName": "New Zealand Dollar",
                "exchangeRate": "5.197278",
                "inverseRate": "0.192408",
                "inverseDescription": "1 New Zealand Dollar = 0.192408 Kuwaiti Dinar"
            },
            {
                "title": "1 KWD = 111.062787 THB",
                "link": "http://www.floatrates.com/kwd/thb/",
                "description": "1 Kuwaiti Dinar = 111.062787 Thai Baht",
                "pubDate": null,
                "baseCurrency": "KWD",
                "baseName": "Kuwaiti Dinar",
                "targetCurrency": "THB",
                "targetName": "Thai Baht",
                "exchangeRate": "111.062787",
                "inverseRate": "0.009004",
                "inverseDescription": "1 Thai Baht = 0.009004 Kuwaiti Dinar"
            },
            {
                "title": "1 KWD = 76,760.950445 VND",
                "link": "http://www.floatrates.com/kwd/vnd/",
                "description": "1 Kuwaiti Dinar = 76,760.950445 Vietnamese Dong",
                "pubDate": null,
                "baseCurrency": "KWD",
                "baseName": "Kuwaiti Dinar",
                "targetCurrency": "VND",
                "targetName": "Vietnamese Dong",
                "exchangeRate": "76,760.950445",
                "inverseRate": "0.000013",
                "inverseDescription": "1 Vietnamese Dong = 0.000013 Kuwaiti Dinar"
            },
            {
                "title": "1 KWD = 48,125.089017 IDR",
                "link": "http://www.floatrates.com/kwd/idr/",
                "description": "1 Kuwaiti Dinar = 48,125.089017 Indonesian Rupiah",
                "pubDate": null,
                "baseCurrency": "KWD",
                "baseName": "Kuwaiti Dinar",
                "targetCurrency": "IDR",
                "targetName": "Indonesian Rupiah",
                "exchangeRate": "48,125.089017",
                "inverseRate": "0.000021",
                "inverseDescription": "1 Indonesian Rupiah = 0.000021 Kuwaiti Dinar"
            },
            {
                "title": "1 KWD = 25.692227 HKD",
                "link": "http://www.floatrates.com/kwd/hkd/",
                "description": "1 Kuwaiti Dinar = 25.692227 Hong Kong Dollar",
                "pubDate": null,
                "baseCurrency": "KWD",
                "baseName": "Kuwaiti Dinar",
                "targetCurrency": "HKD",
                "targetName": "Hong Kong Dollar",
                "exchangeRate": "25.692227",
                "inverseRate": "0.038922",
                "inverseDescription": "1 Hong Kong Dollar = 0.038922 Kuwaiti Dinar"
            },
            {
                "title": "1 KWD = 180.824055 PHP",
                "link": "http://www.floatrates.com/kwd/php/",
                "description": "1 Kuwaiti Dinar = 180.824055 Philippine Peso",
                "pubDate": null,
                "baseCurrency": "KWD",
                "baseName": "Kuwaiti Dinar",
                "targetCurrency": "PHP",
                "targetName": "Philippine Peso",
                "exchangeRate": "180.824055",
                "inverseRate": "0.005530",
                "inverseDescription": "1 Philippine Peso = 0.005530 Kuwaiti Dinar"
            },
            {
                "title": "1 KWD = 1,949.826282 XAF",
                "link": "http://www.floatrates.com/kwd/xaf/",
                "description": "1 Kuwaiti Dinar = 1,949.826282 Central African CFA Franc",
                "pubDate": null,
                "baseCurrency": "KWD",
                "baseName": "Kuwaiti Dinar",
                "targetCurrency": "XAF",
                "targetName": "Central African CFA Franc",
                "exchangeRate": "1,949.826282",
                "inverseRate": "0.000513",
                "inverseDescription": "1 Central African CFA Franc = 0.000513 Kuwaiti Dinar"
            },
            {
                "title": "1 KWD = 1,501.789626 NGN",
                "link": "http://www.floatrates.com/kwd/ngn/",
                "description": "1 Kuwaiti Dinar = 1,501.789626 Nigerian Naira",
                "pubDate": null,
                "baseCurrency": "KWD",
                "baseName": "Kuwaiti Dinar",
                "targetCurrency": "NGN",
                "targetName": "Nigerian Naira",
                "exchangeRate": "1,501.789626",
                "inverseRate": "0.000666",
                "inverseDescription": "1 Nigerian Naira = 0.000666 Kuwaiti Dinar"
            },
            {
                "title": "1 KWD = 11.936767 ILS",
                "link": "http://www.floatrates.com/kwd/ils/",
                "description": "1 Kuwaiti Dinar = 11.936767 Israeli New Sheqel",
                "pubDate": null,
                "baseCurrency": "KWD",
                "baseName": "Kuwaiti Dinar",
                "targetCurrency": "ILS",
                "targetName": "Israeli New Sheqel",
                "exchangeRate": "11.936767",
                "inverseRate": "0.083775",
                "inverseDescription": "1 Israeli New Sheqel = 0.083775 Kuwaiti Dinar"
            },
            {
                "title": "1 KWD = 49,283.662219 LBP",
                "link": "http://www.floatrates.com/kwd/lbp/",
                "description": "1 Kuwaiti Dinar = 49,283.662219 Lebanese Pound",
                "pubDate": null,
                "baseCurrency": "KWD",
                "baseName": "Kuwaiti Dinar",
                "targetCurrency": "LBP",
                "targetName": "Lebanese Pound",
                "exchangeRate": "49,283.662219",
                "inverseRate": "0.000020",
                "inverseDescription": "1 Lebanese Pound = 0.000020 Kuwaiti Dinar"
            },
            {
                "title": "1 KWD = 1,107.422879 HUF",
                "link": "http://www.floatrates.com/kwd/huf/",
                "description": "1 Kuwaiti Dinar = 1,107.422879 Hungarian Forint",
                "pubDate": null,
                "baseCurrency": "KWD",
                "baseName": "Kuwaiti Dinar",
                "targetCurrency": "HUF",
                "targetName": "Hungarian Forint",
                "exchangeRate": "1,107.422879",
                "inverseRate": "0.000903",
                "inverseDescription": "1 Hungarian Forint = 0.000903 Kuwaiti Dinar"
            },
            {
                "title": "1 KWD = 120.489836 UAH",
                "link": "http://www.floatrates.com/kwd/uah/",
                "description": "1 Kuwaiti Dinar = 120.489836 Ukrainian Hryvnia",
                "pubDate": null,
                "baseCurrency": "KWD",
                "baseName": "Kuwaiti Dinar",
                "targetCurrency": "UAH",
                "targetName": "Ukrainian Hryvnia",
                "exchangeRate": "120.489836",
                "inverseRate": "0.008299",
                "inverseDescription": "1 Ukrainian Hryvnia = 0.008299 Kuwaiti Dinar"
            },
            {
                "title": "1 KWD = 69.555555 CZK",
                "link": "http://www.floatrates.com/kwd/czk/",
                "description": "1 Kuwaiti Dinar = 69.555555 Czech Koruna",
                "pubDate": null,
                "baseCurrency": "KWD",
                "baseName": "Kuwaiti Dinar",
                "targetCurrency": "CZK",
                "targetName": "Czech Koruna",
                "exchangeRate": "69.555555",
                "inverseRate": "0.014377",
                "inverseDescription": "1 Czech Koruna = 0.014377 Kuwaiti Dinar"
            },
            {
                "title": "1 KWD = 446.085750 ISK",
                "link": "http://www.floatrates.com/kwd/isk/",
                "description": "1 Kuwaiti Dinar = 446.085750 Icelandic Krona",
                "pubDate": null,
                "baseCurrency": "KWD",
                "baseName": "Kuwaiti Dinar",
                "targetCurrency": "ISK",
                "targetName": "Icelandic Krona",
                "exchangeRate": "446.085750",
                "inverseRate": "0.002242",
                "inverseDescription": "1 Icelandic Krona = 0.002242 Kuwaiti Dinar"
            },
            {
                "title": "1 KWD = 14.645092 RON",
                "link": "http://www.floatrates.com/kwd/ron/",
                "description": "1 Kuwaiti Dinar = 14.645092 Romanian New Leu",
                "pubDate": null,
                "baseCurrency": "KWD",
                "baseName": "Kuwaiti Dinar",
                "targetCurrency": "RON",
                "targetName": "Romanian New Leu",
                "exchangeRate": "14.645092",
                "inverseRate": "0.068282",
                "inverseDescription": "1 Romanian New Leu = 0.068282 Kuwaiti Dinar"
            },
            {
                "title": "1 KWD = 5.812130 BGN",
                "link": "http://www.floatrates.com/kwd/bgn/",
                "description": "1 Kuwaiti Dinar = 5.812130 Bulgarian Lev",
                "pubDate": null,
                "baseCurrency": "KWD",
                "baseName": "Kuwaiti Dinar",
                "targetCurrency": "BGN",
                "targetName": "Bulgarian Lev",
                "exchangeRate": "5.812130",
                "inverseRate": "0.172054",
                "inverseDescription": "1 Bulgarian Lev = 0.172054 Kuwaiti Dinar"
            },
            {
                "title": "1 KWD = 2,615.365097 CLP",
                "link": "http://www.floatrates.com/kwd/clp/",
                "description": "1 Kuwaiti Dinar = 2,615.365097 Chilean Peso",
                "pubDate": null,
                "baseCurrency": "KWD",
                "baseName": "Kuwaiti Dinar",
                "targetCurrency": "CLP",
                "targetName": "Chilean Peso",
                "exchangeRate": "2,615.365097",
                "inverseRate": "0.000382",
                "inverseDescription": "1 Chilean Peso = 0.000382 Kuwaiti Dinar"
            },
            {
                "title": "1 KWD = 58.414470 MXN",
                "link": "http://www.floatrates.com/kwd/mxn/",
                "description": "1 Kuwaiti Dinar = 58.414470 Mexican Peso",
                "pubDate": null,
                "baseCurrency": "KWD",
                "baseName": "Kuwaiti Dinar",
                "targetCurrency": "MXN",
                "targetName": "Mexican Peso",
                "exchangeRate": "58.414470",
                "inverseRate": "0.017119",
                "inverseDescription": "1 Mexican Peso = 0.017119 Kuwaiti Dinar"
            },
            {
                "title": "1 KWD = 284.785270 AFN",
                "link": "http://www.floatrates.com/kwd/afn/",
                "description": "1 Kuwaiti Dinar = 284.785270 Afghan afghani",
                "pubDate": null,
                "baseCurrency": "KWD",
                "baseName": "Kuwaiti Dinar",
                "targetCurrency": "AFN",
                "targetName": "Afghan afghani",
                "exchangeRate": "284.785270",
                "inverseRate": "0.003511",
                "inverseDescription": "1 Afghan afghani = 0.003511 Kuwaiti Dinar"
            },
            {
                "title": "1 KWD = 14,324.309799 MGA",
                "link": "http://www.floatrates.com/kwd/mga/",
                "description": "1 Kuwaiti Dinar = 14,324.309799 Malagasy ariary",
                "pubDate": null,
                "baseCurrency": "KWD",
                "baseName": "Kuwaiti Dinar",
                "targetCurrency": "MGA",
                "targetName": "Malagasy ariary",
                "exchangeRate": "14,324.309799",
                "inverseRate": "0.000070",
                "inverseDescription": "1 Malagasy ariary = 0.000070 Kuwaiti Dinar"
            },
            {
                "title": "1 KWD = 3.258661 PAB",
                "link": "http://www.floatrates.com/kwd/pab/",
                "description": "1 Kuwaiti Dinar = 3.258661 Panamanian Balboa",
                "pubDate": null,
                "baseCurrency": "KWD",
                "baseName": "Kuwaiti Dinar",
                "targetCurrency": "PAB",
                "targetName": "Panamanian Balboa",
                "exchangeRate": "3.258661",
                "inverseRate": "0.306875",
                "inverseDescription": "1 Panamanian Balboa = 0.306875 Kuwaiti Dinar"
            },
            {
                "title": "1 KWD = 177.838363 ETB",
                "link": "http://www.floatrates.com/kwd/etb/",
                "description": "1 Kuwaiti Dinar = 177.838363 Ethiopian birr",
                "pubDate": null,
                "baseCurrency": "KWD",
                "baseName": "Kuwaiti Dinar",
                "targetCurrency": "ETB",
                "targetName": "Ethiopian birr",
                "exchangeRate": "177.838363",
                "inverseRate": "0.005623",
                "inverseDescription": "1 Ethiopian birr = 0.005623 Kuwaiti Dinar"
            },
            {
                "title": "1 KWD = 80.708271 VES",
                "link": "http://www.floatrates.com/kwd/ves/",
                "description": "1 Kuwaiti Dinar = 80.708271 Venezuelan Bolivar",
                "pubDate": null,
                "baseCurrency": "KWD",
                "baseName": "Kuwaiti Dinar",
                "targetCurrency": "VES",
                "targetName": "Venezuelan Bolivar",
                "exchangeRate": "80.708271",
                "inverseRate": "0.012390",
                "inverseDescription": "1 Venezuelan Bolivar = 0.012390 Kuwaiti Dinar"
            },
            {
                "title": "1 KWD = 22.572115 BOB",
                "link": "http://www.floatrates.com/kwd/bob/",
                "description": "1 Kuwaiti Dinar = 22.572115 Bolivian Boliviano",
                "pubDate": null,
                "baseCurrency": "KWD",
                "baseName": "Kuwaiti Dinar",
                "targetCurrency": "BOB",
                "targetName": "Bolivian Boliviano",
                "exchangeRate": "22.572115",
                "inverseRate": "0.044302",
                "inverseDescription": "1 Bolivian Boliviano = 0.044302 Kuwaiti Dinar"
            },
            {
                "title": "1 KWD = 1,765.956205 CRC",
                "link": "http://www.floatrates.com/kwd/crc/",
                "description": "1 Kuwaiti Dinar = 1,765.956205 Costa Rican Col\u00f3n",
                "pubDate": null,
                "baseCurrency": "KWD",
                "baseName": "Kuwaiti Dinar",
                "targetCurrency": "CRC",
                "targetName": "Costa Rican Col\u00f3n",
                "exchangeRate": "1,765.956205",
                "inverseRate": "0.000566",
                "inverseDescription": "1 Costa Rican Col\u00f3n = 0.000566 Kuwaiti Dinar"
            },
            {
                "title": "1 KWD = 28.546560 SVC",
                "link": "http://www.floatrates.com/kwd/svc/",
                "description": "1 Kuwaiti Dinar = 28.546560 Salvadoran colon",
                "pubDate": null,
                "baseCurrency": "KWD",
                "baseName": "Kuwaiti Dinar",
                "targetCurrency": "SVC",
                "targetName": "Salvadoran colon",
                "exchangeRate": "28.546560",
                "inverseRate": "0.035030",
                "inverseDescription": "1 Salvadoran colon = 0.035030 Kuwaiti Dinar"
            },
            {
                "title": "1 KWD = 119.285627 NIO",
                "link": "http://www.floatrates.com/kwd/nio/",
                "description": "1 Kuwaiti Dinar = 119.285627 Nicaraguan C\u00f3rdoba",
                "pubDate": null,
                "baseCurrency": "KWD",
                "baseName": "Kuwaiti Dinar",
                "targetCurrency": "NIO",
                "targetName": "Nicaraguan C\u00f3rdoba",
                "exchangeRate": "119.285627",
                "inverseRate": "0.008383",
                "inverseDescription": "1 Nicaraguan C\u00f3rdoba = 0.008383 Kuwaiti Dinar"
            },
            {
                "title": "1 KWD = 203.928422 GMD",
                "link": "http://www.floatrates.com/kwd/gmd/",
                "description": "1 Kuwaiti Dinar = 203.928422 Gambian dalasi",
                "pubDate": null,
                "baseCurrency": "KWD",
                "baseName": "Kuwaiti Dinar",
                "targetCurrency": "GMD",
                "targetName": "Gambian dalasi",
                "exchangeRate": "203.928422",
                "inverseRate": "0.004904",
                "inverseDescription": "1 Gambian dalasi = 0.004904 Kuwaiti Dinar"
            },
            {
                "title": "1 KWD = 182.836532 MKD",
                "link": "http://www.floatrates.com/kwd/mkd/",
                "description": "1 Kuwaiti Dinar = 182.836532 Macedonian denar",
                "pubDate": null,
                "baseCurrency": "KWD",
                "baseName": "Kuwaiti Dinar",
                "targetCurrency": "MKD",
                "targetName": "Macedonian denar",
                "exchangeRate": "182.836532",
                "inverseRate": "0.005469",
                "inverseDescription": "1 Macedonian denar = 0.005469 Kuwaiti Dinar"
            },
            {
                "title": "1 KWD = 4,280.099417 IQD",
                "link": "http://www.floatrates.com/kwd/iqd/",
                "description": "1 Kuwaiti Dinar = 4,280.099417 Iraqi dinar",
                "pubDate": null,
                "baseCurrency": "KWD",
                "baseName": "Kuwaiti Dinar",
                "targetCurrency": "IQD",
                "targetName": "Iraqi dinar",
                "exchangeRate": "4,280.099417",
                "inverseRate": "0.000234",
                "inverseDescription": "1 Iraqi dinar = 0.000234 Kuwaiti Dinar"
            },
            {
                "title": "1 KWD = 348.789702 RSD",
                "link": "http://www.floatrates.com/kwd/rsd/",
                "description": "1 Kuwaiti Dinar = 348.789702 Serbian Dinar",
                "pubDate": null,
                "baseCurrency": "KWD",
                "baseName": "Kuwaiti Dinar",
                "targetCurrency": "RSD",
                "targetName": "Serbian Dinar",
                "exchangeRate": "348.789702",
                "inverseRate": "0.002867",
                "inverseDescription": "1 Serbian Dinar = 0.002867 Kuwaiti Dinar"
            },
            {
                "title": "1 KWD = 73.475829 STN",
                "link": "http://www.floatrates.com/kwd/stn/",
                "description": "1 Kuwaiti Dinar = 73.475829 S\u00e3o Tom\u00e9 and Pr\u00edncipe Dobra",
                "pubDate": null,
                "baseCurrency": "KWD",
                "baseName": "Kuwaiti Dinar",
                "targetCurrency": "STN",
                "targetName": "S\u00e3o Tom\u00e9 and Pr\u00edncipe Dobra",
                "exchangeRate": "73.475829",
                "inverseRate": "0.013610",
                "inverseDescription": "1 S\u00e3o Tom\u00e9 and Pr\u00edncipe Dobra = 0.013610 Kuwaiti Dinar"
            },
            {
                "title": "1 KWD = 3.257160 BSD",
                "link": "http://www.floatrates.com/kwd/bsd/",
                "description": "1 Kuwaiti Dinar = 3.257160 Bahamian Dollar",
                "pubDate": null,
                "baseCurrency": "KWD",
                "baseName": "Kuwaiti Dinar",
                "targetCurrency": "BSD",
                "targetName": "Bahamian Dollar",
                "exchangeRate": "3.257160",
                "inverseRate": "0.307016",
                "inverseDescription": "1 Bahamian Dollar = 0.307016 Kuwaiti Dinar"
            },
            {
                "title": "1 KWD = 6.584378 BBD",
                "link": "http://www.floatrates.com/kwd/bbd/",
                "description": "1 Kuwaiti Dinar = 6.584378 Barbadian Dollar",
                "pubDate": null,
                "baseCurrency": "KWD",
                "baseName": "Kuwaiti Dinar",
                "targetCurrency": "BBD",
                "targetName": "Barbadian Dollar",
                "exchangeRate": "6.584378",
                "inverseRate": "0.151875",
                "inverseDescription": "1 Barbadian Dollar = 0.151875 Kuwaiti Dinar"
            },
            {
                "title": "1 KWD = 6.573257 BZD",
                "link": "http://www.floatrates.com/kwd/bzd/",
                "description": "1 Kuwaiti Dinar = 6.573257 Belize dollar",
                "pubDate": null,
                "baseCurrency": "KWD",
                "baseName": "Kuwaiti Dinar",
                "targetCurrency": "BZD",
                "targetName": "Belize dollar",
                "exchangeRate": "6.573257",
                "inverseRate": "0.152132",
                "inverseDescription": "1 Belize dollar = 0.152132 Kuwaiti Dinar"
            },
            {
                "title": "1 KWD = 4.355132 BND",
                "link": "http://www.floatrates.com/kwd/bnd/",
                "description": "1 Kuwaiti Dinar = 4.355132 Brunei Dollar",
                "pubDate": null,
                "baseCurrency": "KWD",
                "baseName": "Kuwaiti Dinar",
                "targetCurrency": "BND",
                "targetName": "Brunei Dollar",
                "exchangeRate": "4.355132",
                "inverseRate": "0.229614",
                "inverseDescription": "1 Brunei Dollar = 0.229614 Kuwaiti Dinar"
            },
            {
                "title": "1 KWD = 7.226364 FJD",
                "link": "http://www.floatrates.com/kwd/fjd/",
                "description": "1 Kuwaiti Dinar = 7.226364 Fiji Dollar",
                "pubDate": null,
                "baseCurrency": "KWD",
                "baseName": "Kuwaiti Dinar",
                "targetCurrency": "FJD",
                "targetName": "Fiji Dollar",
                "exchangeRate": "7.226364",
                "inverseRate": "0.138382",
                "inverseDescription": "1 Fiji Dollar = 0.138382 Kuwaiti Dinar"
            },
            {
                "title": "1 KWD = 689.707793 GYD",
                "link": "http://www.floatrates.com/kwd/gyd/",
                "description": "1 Kuwaiti Dinar = 689.707793 Guyanese dollar",
                "pubDate": null,
                "baseCurrency": "KWD",
                "baseName": "Kuwaiti Dinar",
                "targetCurrency": "GYD",
                "targetName": "Guyanese dollar",
                "exchangeRate": "689.707793",
                "inverseRate": "0.001450",
                "inverseDescription": "1 Guyanese dollar = 0.001450 Kuwaiti Dinar"
            },
            {
                "title": "1 KWD = 498.989693 JMD",
                "link": "http://www.floatrates.com/kwd/jmd/",
                "description": "1 Kuwaiti Dinar = 498.989693 Jamaican Dollar",
                "pubDate": null,
                "baseCurrency": "KWD",
                "baseName": "Kuwaiti Dinar",
                "targetCurrency": "JMD",
                "targetName": "Jamaican Dollar",
                "exchangeRate": "498.989693",
                "inverseRate": "0.002004",
                "inverseDescription": "1 Jamaican Dollar = 0.002004 Kuwaiti Dinar"
            },
            {
                "title": "1 KWD = 544.896745 LRD",
                "link": "http://www.floatrates.com/kwd/lrd/",
                "description": "1 Kuwaiti Dinar = 544.896745 Liberian dollar",
                "pubDate": null,
                "baseCurrency": "KWD",
                "baseName": "Kuwaiti Dinar",
                "targetCurrency": "LRD",
                "targetName": "Liberian dollar",
                "exchangeRate": "544.896745",
                "inverseRate": "0.001835",
                "inverseDescription": "1 Liberian dollar = 0.001835 Kuwaiti Dinar"
            },
            {
                "title": "1 KWD = 59.957828 NAD",
                "link": "http://www.floatrates.com/kwd/nad/",
                "description": "1 Kuwaiti Dinar = 59.957828 Namibian dollar",
                "pubDate": null,
                "baseCurrency": "KWD",
                "baseName": "Kuwaiti Dinar",
                "targetCurrency": "NAD",
                "targetName": "Namibian dollar",
                "exchangeRate": "59.957828",
                "inverseRate": "0.016678",
                "inverseDescription": "1 Namibian dollar = 0.016678 Kuwaiti Dinar"
            },
            {
                "title": "1 KWD = 120.980627 SRD",
                "link": "http://www.floatrates.com/kwd/srd/",
                "description": "1 Kuwaiti Dinar = 120.980627 Surinamese dollar",
                "pubDate": null,
                "baseCurrency": "KWD",
                "baseName": "Kuwaiti Dinar",
                "targetCurrency": "SRD",
                "targetName": "Surinamese dollar",
                "exchangeRate": "120.980627",
                "inverseRate": "0.008266",
                "inverseDescription": "1 Surinamese dollar = 0.008266 Kuwaiti Dinar"
            },
            {
                "title": "1 KWD = 22.103551 TTD",
                "link": "http://www.floatrates.com/kwd/ttd/",
                "description": "1 Kuwaiti Dinar = 22.103551 Trinidad Tobago Dollar",
                "pubDate": null,
                "baseCurrency": "KWD",
                "baseName": "Kuwaiti Dinar",
                "targetCurrency": "TTD",
                "targetName": "Trinidad Tobago Dollar",
                "exchangeRate": "22.103551",
                "inverseRate": "0.045242",
                "inverseDescription": "1 Trinidad Tobago Dollar = 0.045242 Kuwaiti Dinar"
            },
            {
                "title": "1 KWD = 8.845726 XCD",
                "link": "http://www.floatrates.com/kwd/xcd/",
                "description": "1 Kuwaiti Dinar = 8.845726 East Caribbean Dollar",
                "pubDate": null,
                "baseCurrency": "KWD",
                "baseName": "Kuwaiti Dinar",
                "targetCurrency": "XCD",
                "targetName": "East Caribbean Dollar",
                "exchangeRate": "8.845726",
                "inverseRate": "0.113049",
                "inverseDescription": "1 East Caribbean Dollar = 0.113049 Kuwaiti Dinar"
            },
            {
                "title": "1 KWD = 26.863377 SBD",
                "link": "http://www.floatrates.com/kwd/sbd/",
                "description": "1 Kuwaiti Dinar = 26.863377 Solomon Islands dollar",
                "pubDate": null,
                "baseCurrency": "KWD",
                "baseName": "Kuwaiti Dinar",
                "targetCurrency": "SBD",
                "targetName": "Solomon Islands dollar",
                "exchangeRate": "26.863377",
                "inverseRate": "0.037225",
                "inverseDescription": "1 Solomon Islands dollar = 0.037225 Kuwaiti Dinar"
            },
            {
                "title": "1 KWD = 1,263.304256 AMD",
                "link": "http://www.floatrates.com/kwd/amd/",
                "description": "1 Kuwaiti Dinar = 1,263.304256 Armenia Dram",
                "pubDate": null,
                "baseCurrency": "KWD",
                "baseName": "Kuwaiti Dinar",
                "targetCurrency": "AMD",
                "targetName": "Armenia Dram",
                "exchangeRate": "1,263.304256",
                "inverseRate": "0.000792",
                "inverseDescription": "1 Armenia Dram = 0.000792 Kuwaiti Dinar"
            },
            {
                "title": "1 KWD = 329.043928 CVE",
                "link": "http://www.floatrates.com/kwd/cve/",
                "description": "1 Kuwaiti Dinar = 329.043928 Cape Verde escudo",
                "pubDate": null,
                "baseCurrency": "KWD",
                "baseName": "Kuwaiti Dinar",
                "targetCurrency": "CVE",
                "targetName": "Cape Verde escudo",
                "exchangeRate": "329.043928",
                "inverseRate": "0.003039",
                "inverseDescription": "1 Cape Verde escudo = 0.003039 Kuwaiti Dinar"
            },
            {
                "title": "1 KWD = 5.902517 AWG",
                "link": "http://www.floatrates.com/kwd/awg/",
                "description": "1 Kuwaiti Dinar = 5.902517 Aruban florin",
                "pubDate": null,
                "baseCurrency": "KWD",
                "baseName": "Kuwaiti Dinar",
                "targetCurrency": "AWG",
                "targetName": "Aruban florin",
                "exchangeRate": "5.902517",
                "inverseRate": "0.169419",
                "inverseDescription": "1 Aruban florin = 0.169419 Kuwaiti Dinar"
            },
            {
                "title": "1 KWD = 6,790.836799 BIF",
                "link": "http://www.floatrates.com/kwd/bif/",
                "description": "1 Kuwaiti Dinar = 6,790.836799 Burundian franc",
                "pubDate": null,
                "baseCurrency": "KWD",
                "baseName": "Kuwaiti Dinar",
                "targetCurrency": "BIF",
                "targetName": "Burundian franc",
                "exchangeRate": "6,790.836799",
                "inverseRate": "0.000147",
                "inverseDescription": "1 Burundian franc = 0.000147 Kuwaiti Dinar"
            },
            {
                "title": "1 KWD = 354.215472 XPF",
                "link": "http://www.floatrates.com/kwd/xpf/",
                "description": "1 Kuwaiti Dinar = 354.215472 CFP Franc",
                "pubDate": null,
                "baseCurrency": "KWD",
                "baseName": "Kuwaiti Dinar",
                "targetCurrency": "XPF",
                "targetName": "CFP Franc",
                "exchangeRate": "354.215472",
                "inverseRate": "0.002823",
                "inverseDescription": "1 CFP Franc = 0.002823 Kuwaiti Dinar"
            },
            {
                "title": "1 KWD = 580.641005 DJF",
                "link": "http://www.floatrates.com/kwd/djf/",
                "description": "1 Kuwaiti Dinar = 580.641005 Djiboutian franc",
                "pubDate": null,
                "baseCurrency": "KWD",
                "baseName": "Kuwaiti Dinar",
                "targetCurrency": "DJF",
                "targetName": "Djiboutian franc",
                "exchangeRate": "580.641005",
                "inverseRate": "0.001722",
                "inverseDescription": "1 Djiboutian franc = 0.001722 Kuwaiti Dinar"
            },
            {
                "title": "1 KWD = 28,029.667940 GNF",
                "link": "http://www.floatrates.com/kwd/gnf/",
                "description": "1 Kuwaiti Dinar = 28,029.667940 Guinean franc",
                "pubDate": null,
                "baseCurrency": "KWD",
                "baseName": "Kuwaiti Dinar",
                "targetCurrency": "GNF",
                "targetName": "Guinean franc",
                "exchangeRate": "28,029.667940",
                "inverseRate": "0.000036",
                "inverseDescription": "1 Guinean franc = 0.000036 Kuwaiti Dinar"
            },
            {
                "title": "1 KWD = 1,458.034745 KMF",
                "link": "http://www.floatrates.com/kwd/kmf/",
                "description": "1 Kuwaiti Dinar = 1,458.034745 \tComoro franc",
                "pubDate": null,
                "baseCurrency": "KWD",
                "baseName": "Kuwaiti Dinar",
                "targetCurrency": "KMF",
                "targetName": "Comoro franc",
                "exchangeRate": "1,458.034745",
                "inverseRate": "0.000686",
                "inverseDescription": "1 \tComoro franc = 0.000686 Kuwaiti Dinar"
            },
            {
                "title": "1 KWD = 6,658.073616 CDF",
                "link": "http://www.floatrates.com/kwd/cdf/",
                "description": "1 Kuwaiti Dinar = 6,658.073616 Congolese franc",
                "pubDate": null,
                "baseCurrency": "KWD",
                "baseName": "Kuwaiti Dinar",
                "targetCurrency": "CDF",
                "targetName": "Congolese franc",
                "exchangeRate": "6,658.073616",
                "inverseRate": "0.000150",
                "inverseDescription": "1 Congolese franc = 0.000150 Kuwaiti Dinar"
            },
            {
                "title": "1 KWD = 3,629.741172 RWF",
                "link": "http://www.floatrates.com/kwd/rwf/",
                "description": "1 Kuwaiti Dinar = 3,629.741172 Rwandan franc",
                "pubDate": null,
                "baseCurrency": "KWD",
                "baseName": "Kuwaiti Dinar",
                "targetCurrency": "RWF",
                "targetName": "Rwandan franc",
                "exchangeRate": "3,629.741172",
                "inverseRate": "0.000276",
                "inverseDescription": "1 Rwandan franc = 0.000276 Kuwaiti Dinar"
            },
            {
                "title": "1 KWD = 2,754.229401 SSP",
                "link": "http://www.floatrates.com/kwd/ssp/",
                "description": "1 Kuwaiti Dinar = 2,754.229401 South Sudanese pound",
                "pubDate": null,
                "baseCurrency": "KWD",
                "baseName": "Kuwaiti Dinar",
                "targetCurrency": "SSP",
                "targetName": "South Sudanese pound",
                "exchangeRate": "2,754.229401",
                "inverseRate": "0.000363",
                "inverseDescription": "1 South Sudanese pound = 0.000363 Kuwaiti Dinar"
            },
            {
                "title": "1 KWD = 1,946.059803 SDG",
                "link": "http://www.floatrates.com/kwd/sdg/",
                "description": "1 Kuwaiti Dinar = 1,946.059803 Sudanese pound",
                "pubDate": null,
                "baseCurrency": "KWD",
                "baseName": "Kuwaiti Dinar",
                "targetCurrency": "SDG",
                "targetName": "Sudanese pound",
                "exchangeRate": "1,946.059803",
                "inverseRate": "0.000514",
                "inverseDescription": "1 Sudanese pound = 0.000514 Kuwaiti Dinar"
            },
            {
                "title": "1 KWD = 8,013.187423 SYP",
                "link": "http://www.floatrates.com/kwd/syp/",
                "description": "1 Kuwaiti Dinar = 8,013.187423 Syrian pound",
                "pubDate": null,
                "baseCurrency": "KWD",
                "baseName": "Kuwaiti Dinar",
                "targetCurrency": "SYP",
                "targetName": "Syrian pound",
                "exchangeRate": "8,013.187423",
                "inverseRate": "0.000125",
                "inverseDescription": "1 Syrian pound = 0.000125 Kuwaiti Dinar"
            },
            {
                "title": "1 KWD = 38.158035 GHS",
                "link": "http://www.floatrates.com/kwd/ghs/",
                "description": "1 Kuwaiti Dinar = 38.158035 Ghanaian Cedi",
                "pubDate": null,
                "baseCurrency": "KWD",
                "baseName": "Kuwaiti Dinar",
                "targetCurrency": "GHS",
                "targetName": "Ghanaian Cedi",
                "exchangeRate": "38.158035",
                "inverseRate": "0.026207",
                "inverseDescription": "1 Ghanaian Cedi = 0.026207 Kuwaiti Dinar"
            },
            {
                "title": "1 KWD = 502.790551 HTG",
                "link": "http://www.floatrates.com/kwd/htg/",
                "description": "1 Kuwaiti Dinar = 502.790551 Haitian gourde",
                "pubDate": null,
                "baseCurrency": "KWD",
                "baseName": "Kuwaiti Dinar",
                "targetCurrency": "HTG",
                "targetName": "Haitian gourde",
                "exchangeRate": "502.790551",
                "inverseRate": "0.001989",
                "inverseDescription": "1 Haitian gourde = 0.001989 Kuwaiti Dinar"
            },
            {
                "title": "1 KWD = 23,552.283887 PYG",
                "link": "http://www.floatrates.com/kwd/pyg/",
                "description": "1 Kuwaiti Dinar = 23,552.283887 Paraguayan Guaran\u00ed",
                "pubDate": null,
                "baseCurrency": "KWD",
                "baseName": "Kuwaiti Dinar",
                "targetCurrency": "PYG",
                "targetName": "Paraguayan Guaran\u00ed",
                "exchangeRate": "23,552.283887",
                "inverseRate": "0.000042",
                "inverseDescription": "1 Paraguayan Guaran\u00ed = 0.000042 Kuwaiti Dinar"
            },
            {
                "title": "1 KWD = 5.877305 ANG",
                "link": "http://www.floatrates.com/kwd/ang/",
                "description": "1 Kuwaiti Dinar = 5.877305 Neth. Antillean Guilder",
                "pubDate": null,
                "baseCurrency": "KWD",
                "baseName": "Kuwaiti Dinar",
                "targetCurrency": "ANG",
                "targetName": "Neth. Antillean Guilder",
                "exchangeRate": "5.877305",
                "inverseRate": "0.170146",
                "inverseDescription": "1 Neth. Antillean Guilder = 0.170146 Kuwaiti Dinar"
            },
            {
                "title": "1 KWD = 11.490863 PGK",
                "link": "http://www.floatrates.com/kwd/pgk/",
                "description": "1 Kuwaiti Dinar = 11.490863 Papua New Guinean kina",
                "pubDate": null,
                "baseCurrency": "KWD",
                "baseName": "Kuwaiti Dinar",
                "targetCurrency": "PGK",
                "targetName": "Papua New Guinean kina",
                "exchangeRate": "11.490863",
                "inverseRate": "0.087026",
                "inverseDescription": "1 Papua New Guinean kina = 0.087026 Kuwaiti Dinar"
            },
            {
                "title": "1 KWD = 56,760.077578 LAK",
                "link": "http://www.floatrates.com/kwd/lak/",
                "description": "1 Kuwaiti Dinar = 56,760.077578 Lao kip",
                "pubDate": null,
                "baseCurrency": "KWD",
                "baseName": "Kuwaiti Dinar",
                "targetCurrency": "LAK",
                "targetName": "Lao kip",
                "exchangeRate": "56,760.077578",
                "inverseRate": "0.000018",
                "inverseDescription": "1 Lao kip = 0.000018 Kuwaiti Dinar"
            },
            {
                "title": "1 KWD = 3,347.031602 MWK",
                "link": "http://www.floatrates.com/kwd/mwk/",
                "description": "1 Kuwaiti Dinar = 3,347.031602 Malawian kwacha",
                "pubDate": null,
                "baseCurrency": "KWD",
                "baseName": "Kuwaiti Dinar",
                "targetCurrency": "MWK",
                "targetName": "Malawian kwacha",
                "exchangeRate": "3,347.031602",
                "inverseRate": "0.000299",
                "inverseDescription": "1 Malawian kwacha = 0.000299 Kuwaiti Dinar"
            },
            {
                "title": "1 KWD = 57.967739 ZMW",
                "link": "http://www.floatrates.com/kwd/zmw/",
                "description": "1 Kuwaiti Dinar = 57.967739 Zambian kwacha",
                "pubDate": null,
                "baseCurrency": "KWD",
                "baseName": "Kuwaiti Dinar",
                "targetCurrency": "ZMW",
                "targetName": "Zambian kwacha",
                "exchangeRate": "57.967739",
                "inverseRate": "0.017251",
                "inverseDescription": "1 Zambian kwacha = 0.017251 Kuwaiti Dinar"
            },
            {
                "title": "1 KWD = 1,681.780076 AOA",
                "link": "http://www.floatrates.com/kwd/aoa/",
                "description": "1 Kuwaiti Dinar = 1,681.780076 Angolan kwanza",
                "pubDate": null,
                "baseCurrency": "KWD",
                "baseName": "Kuwaiti Dinar",
                "targetCurrency": "AOA",
                "targetName": "Angolan kwanza",
                "exchangeRate": "1,681.780076",
                "inverseRate": "0.000595",
                "inverseDescription": "1 Angolan kwanza = 0.000595 Kuwaiti Dinar"
            },
            {
                "title": "1 KWD = 6,848.878139 MMK",
                "link": "http://www.floatrates.com/kwd/mmk/",
                "description": "1 Kuwaiti Dinar = 6,848.878139 Myanma Kyat",
                "pubDate": null,
                "baseCurrency": "KWD",
                "baseName": "Kuwaiti Dinar",
                "targetCurrency": "MMK",
                "targetName": "Myanma Kyat",
                "exchangeRate": "6,848.878139",
                "inverseRate": "0.000146",
                "inverseDescription": "1 Myanma Kyat = 0.000146 Kuwaiti Dinar"
            },
            {
                "title": "1 KWD = 8.137680 GEL",
                "link": "http://www.floatrates.com/kwd/gel/",
                "description": "1 Kuwaiti Dinar = 8.137680 Georgian lari",
                "pubDate": null,
                "baseCurrency": "KWD",
                "baseName": "Kuwaiti Dinar",
                "targetCurrency": "GEL",
                "targetName": "Georgian lari",
                "exchangeRate": "8.137680",
                "inverseRate": "0.122885",
                "inverseDescription": "1 Georgian lari = 0.122885 Kuwaiti Dinar"
            },
            {
                "title": "1 KWD = 58.600035 MDL",
                "link": "http://www.floatrates.com/kwd/mdl/",
                "description": "1 Kuwaiti Dinar = 58.600035 Moldova Lei",
                "pubDate": null,
                "baseCurrency": "KWD",
                "baseName": "Kuwaiti Dinar",
                "targetCurrency": "MDL",
                "targetName": "Moldova Lei",
                "exchangeRate": "58.600035",
                "inverseRate": "0.017065",
                "inverseDescription": "1 Moldova Lei = 0.017065 Kuwaiti Dinar"
            },
            {
                "title": "1 KWD = 329.593250 ALL",
                "link": "http://www.floatrates.com/kwd/all/",
                "description": "1 Kuwaiti Dinar = 329.593250 Albanian lek",
                "pubDate": null,
                "baseCurrency": "KWD",
                "baseName": "Kuwaiti Dinar",
                "targetCurrency": "ALL",
                "targetName": "Albanian lek",
                "exchangeRate": "329.593250",
                "inverseRate": "0.003034",
                "inverseDescription": "1 Albanian lek = 0.003034 Kuwaiti Dinar"
            },
            {
                "title": "1 KWD = 80.131874 HNL",
                "link": "http://www.floatrates.com/kwd/hnl/",
                "description": "1 Kuwaiti Dinar = 80.131874 Honduran Lempira",
                "pubDate": null,
                "baseCurrency": "KWD",
                "baseName": "Kuwaiti Dinar",
                "targetCurrency": "HNL",
                "targetName": "Honduran Lempira",
                "exchangeRate": "80.131874",
                "inverseRate": "0.012479",
                "inverseDescription": "1 Honduran Lempira = 0.012479 Kuwaiti Dinar"
            },
            {
                "title": "1 KWD = 59.957828 SZL",
                "link": "http://www.floatrates.com/kwd/szl/",
                "description": "1 Kuwaiti Dinar = 59.957828 Swazi lilangeni",
                "pubDate": null,
                "baseCurrency": "KWD",
                "baseName": "Kuwaiti Dinar",
                "targetCurrency": "SZL",
                "targetName": "Swazi lilangeni",
                "exchangeRate": "59.957828",
                "inverseRate": "0.016678",
                "inverseDescription": "1 Swazi lilangeni = 0.016678 Kuwaiti Dinar"
            },
            {
                "title": "1 KWD = 59.957828 LSL",
                "link": "http://www.floatrates.com/kwd/lsl/",
                "description": "1 Kuwaiti Dinar = 59.957828 Lesotho loti",
                "pubDate": null,
                "baseCurrency": "KWD",
                "baseName": "Kuwaiti Dinar",
                "targetCurrency": "LSL",
                "targetName": "Lesotho loti",
                "exchangeRate": "59.957828",
                "inverseRate": "0.016678",
                "inverseDescription": "1 Lesotho loti = 0.016678 Kuwaiti Dinar"
            },
            {
                "title": "1 KWD = 5.550474 AZN",
                "link": "http://www.floatrates.com/kwd/azn/",
                "description": "1 Kuwaiti Dinar = 5.550474 Azerbaijan Manat",
                "pubDate": null,
                "baseCurrency": "KWD",
                "baseName": "Kuwaiti Dinar",
                "targetCurrency": "AZN",
                "targetName": "Azerbaijan Manat",
                "exchangeRate": "5.550474",
                "inverseRate": "0.180165",
                "inverseDescription": "1 Azerbaijan Manat = 0.180165 Kuwaiti Dinar"
            },
            {
                "title": "1 KWD = 209.253742 MZN",
                "link": "http://www.floatrates.com/kwd/mzn/",
                "description": "1 Kuwaiti Dinar = 209.253742 Mozambican metical",
                "pubDate": null,
                "baseCurrency": "KWD",
                "baseName": "Kuwaiti Dinar",
                "targetCurrency": "MZN",
                "targetName": "Mozambican metical",
                "exchangeRate": "209.253742",
                "inverseRate": "0.004779",
                "inverseDescription": "1 Mozambican metical = 0.004779 Kuwaiti Dinar"
            },
            {
                "title": "1 KWD = 49.178407 ERN",
                "link": "http://www.floatrates.com/kwd/ern/",
                "description": "1 Kuwaiti Dinar = 49.178407 Eritrean nakfa",
                "pubDate": null,
                "baseCurrency": "KWD",
                "baseName": "Kuwaiti Dinar",
                "targetCurrency": "ERN",
                "targetName": "Eritrean nakfa",
                "exchangeRate": "49.178407",
                "inverseRate": "0.020334",
                "inverseDescription": "1 Eritrean nakfa = 0.020334 Kuwaiti Dinar"
            },
            {
                "title": "1 KWD = 11.428196 TMT",
                "link": "http://www.floatrates.com/kwd/tmt/",
                "description": "1 Kuwaiti Dinar = 11.428196 New Turkmenistan Manat",
                "pubDate": null,
                "baseCurrency": "KWD",
                "baseName": "Kuwaiti Dinar",
                "targetCurrency": "TMT",
                "targetName": "New Turkmenistan Manat",
                "exchangeRate": "11.428196",
                "inverseRate": "0.087503",
                "inverseDescription": "1 New Turkmenistan Manat = 0.087503 Kuwaiti Dinar"
            },
            {
                "title": "1 KWD = 111.934418 MRU",
                "link": "http://www.floatrates.com/kwd/mru/",
                "description": "1 Kuwaiti Dinar = 111.934418 Mauritanian ouguiya",
                "pubDate": null,
                "baseCurrency": "KWD",
                "baseName": "Kuwaiti Dinar",
                "targetCurrency": "MRU",
                "targetName": "Mauritanian ouguiya",
                "exchangeRate": "111.934418",
                "inverseRate": "0.008934",
                "inverseDescription": "1 Mauritanian ouguiya = 0.008934 Kuwaiti Dinar"
            },
            {
                "title": "1 KWD = 7.688029 TOP",
                "link": "http://www.floatrates.com/kwd/top/",
                "description": "1 Kuwaiti Dinar = 7.688029 Tongan pa\u02bbanga",
                "pubDate": null,
                "baseCurrency": "KWD",
                "baseName": "Kuwaiti Dinar",
                "targetCurrency": "TOP",
                "targetName": "Tongan pa\u02bbanga",
                "exchangeRate": "7.688029",
                "inverseRate": "0.130072",
                "inverseDescription": "1 Tongan pa\u02bbanga = 0.130072 Kuwaiti Dinar"
            },
            {
                "title": "1 KWD = 26.379587 MOP",
                "link": "http://www.floatrates.com/kwd/mop/",
                "description": "1 Kuwaiti Dinar = 26.379587 Macanese pataca",
                "pubDate": null,
                "baseCurrency": "KWD",
                "baseName": "Kuwaiti Dinar",
                "targetCurrency": "MOP",
                "targetName": "Macanese pataca",
                "exchangeRate": "26.379587",
                "inverseRate": "0.037908",
                "inverseDescription": "1 Macanese pataca = 0.037908 Kuwaiti Dinar"
            },
            {
                "title": "1 KWD = 726.036639 ARS",
                "link": "http://www.floatrates.com/kwd/ars/",
                "description": "1 Kuwaiti Dinar = 726.036639 Argentine Peso",
                "pubDate": null,
                "baseCurrency": "KWD",
                "baseName": "Kuwaiti Dinar",
                "targetCurrency": "ARS",
                "targetName": "Argentine Peso",
                "exchangeRate": "726.036639",
                "inverseRate": "0.001377",
                "inverseDescription": "1 Argentine Peso = 0.001377 Kuwaiti Dinar"
            },
            {
                "title": "1 KWD = 178.073738 DOP",
                "link": "http://www.floatrates.com/kwd/dop/",
                "description": "1 Kuwaiti Dinar = 178.073738 Dominican Peso",
                "pubDate": null,
                "baseCurrency": "KWD",
                "baseName": "Kuwaiti Dinar",
                "targetCurrency": "DOP",
                "targetName": "Dominican Peso",
                "exchangeRate": "178.073738",
                "inverseRate": "0.005616",
                "inverseDescription": "1 Dominican Peso = 0.005616 Kuwaiti Dinar"
            },
            {
                "title": "1 KWD = 15,304.834407 COP",
                "link": "http://www.floatrates.com/kwd/cop/",
                "description": "1 Kuwaiti Dinar = 15,304.834407 Colombian Peso",
                "pubDate": null,
                "baseCurrency": "KWD",
                "baseName": "Kuwaiti Dinar",
                "targetCurrency": "COP",
                "targetName": "Colombian Peso",
                "exchangeRate": "15,304.834407",
                "inverseRate": "0.000065",
                "inverseDescription": "1 Colombian Peso = 0.000065 Kuwaiti Dinar"
            },
            {
                "title": "1 KWD = 3.257160 CUP",
                "link": "http://www.floatrates.com/kwd/cup/",
                "description": "1 Kuwaiti Dinar = 3.257160 Cuban peso",
                "pubDate": null,
                "baseCurrency": "KWD",
                "baseName": "Kuwaiti Dinar",
                "targetCurrency": "CUP",
                "targetName": "Cuban peso",
                "exchangeRate": "3.257160",
                "inverseRate": "0.307016",
                "inverseDescription": "1 Cuban peso = 0.307016 Kuwaiti Dinar"
            },
            {
                "title": "1 KWD = 126.550652 UYU",
                "link": "http://www.floatrates.com/kwd/uyu/",
                "description": "1 Kuwaiti Dinar = 126.550652 Uruguayan Peso",
                "pubDate": null,
                "baseCurrency": "KWD",
                "baseName": "Kuwaiti Dinar",
                "targetCurrency": "UYU",
                "targetName": "Uruguayan Peso",
                "exchangeRate": "126.550652",
                "inverseRate": "0.007902",
                "inverseDescription": "1 Uruguayan Peso = 0.007902 Kuwaiti Dinar"
            },
            {
                "title": "1 KWD = 43.190928 BWP",
                "link": "http://www.floatrates.com/kwd/bwp/",
                "description": "1 Kuwaiti Dinar = 43.190928 Botswana Pula",
                "pubDate": null,
                "baseCurrency": "KWD",
                "baseName": "Kuwaiti Dinar",
                "targetCurrency": "BWP",
                "targetName": "Botswana Pula",
                "exchangeRate": "43.190928",
                "inverseRate": "0.023153",
                "inverseDescription": "1 Botswana Pula = 0.023153 Kuwaiti Dinar"
            },
            {
                "title": "1 KWD = 25.452950 GTQ",
                "link": "http://www.floatrates.com/kwd/gtq/",
                "description": "1 Kuwaiti Dinar = 25.452950 Guatemalan Quetzal",
                "pubDate": null,
                "baseCurrency": "KWD",
                "baseName": "Kuwaiti Dinar",
                "targetCurrency": "GTQ",
                "targetName": "Guatemalan Quetzal",
                "exchangeRate": "25.452950",
                "inverseRate": "0.039288",
                "inverseDescription": "1 Guatemalan Quetzal = 0.039288 Kuwaiti Dinar"
            },
            {
                "title": "1 KWD = 137,547.355378 IRR",
                "link": "http://www.floatrates.com/kwd/irr/",
                "description": "1 Kuwaiti Dinar = 137,547.355378 Iranian rial",
                "pubDate": null,
                "baseCurrency": "KWD",
                "baseName": "Kuwaiti Dinar",
                "targetCurrency": "IRR",
                "targetName": "Iranian rial",
                "exchangeRate": "137,547.355378",
                "inverseRate": "0.000007",
                "inverseDescription": "1 Iranian rial = 0.000007 Kuwaiti Dinar"
            },
            {
                "title": "1 KWD = 816.006866 YER",
                "link": "http://www.floatrates.com/kwd/yer/",
                "description": "1 Kuwaiti Dinar = 816.006866 Yemeni rial",
                "pubDate": null,
                "baseCurrency": "KWD",
                "baseName": "Kuwaiti Dinar",
                "targetCurrency": "YER",
                "targetName": "Yemeni rial",
                "exchangeRate": "816.006866",
                "inverseRate": "0.001225",
                "inverseDescription": "1 Yemeni rial = 0.001225 Kuwaiti Dinar"
            },
            {
                "title": "1 KWD = 13,434.337888 KHR",
                "link": "http://www.floatrates.com/kwd/khr/",
                "description": "1 Kuwaiti Dinar = 13,434.337888 Cambodian riel",
                "pubDate": null,
                "baseCurrency": "KWD",
                "baseName": "Kuwaiti Dinar",
                "targetCurrency": "KHR",
                "targetName": "Cambodian riel",
                "exchangeRate": "13,434.337888",
                "inverseRate": "0.000074",
                "inverseDescription": "1 Cambodian riel = 0.000074 Kuwaiti Dinar"
            },
            {
                "title": "1 KWD = 9.261585 BYN",
                "link": "http://www.floatrates.com/kwd/byn/",
                "description": "1 Kuwaiti Dinar = 9.261585 Belarussian Ruble",
                "pubDate": null,
                "baseCurrency": "KWD",
                "baseName": "Kuwaiti Dinar",
                "targetCurrency": "BYN",
                "targetName": "Belarussian Ruble",
                "exchangeRate": "9.261585",
                "inverseRate": "0.107973",
                "inverseDescription": "1 Belarussian Ruble = 0.107973 Kuwaiti Dinar"
            },
            {
                "title": "1 KWD = 1,045.144899 LKR",
                "link": "http://www.floatrates.com/kwd/lkr/",
                "description": "1 Kuwaiti Dinar = 1,045.144899 Sri Lanka Rupee",
                "pubDate": null,
                "baseCurrency": "KWD",
                "baseName": "Kuwaiti Dinar",
                "targetCurrency": "LKR",
                "targetName": "Sri Lanka Rupee",
                "exchangeRate": "1,045.144899",
                "inverseRate": "0.000957",
                "inverseDescription": "1 Sri Lanka Rupee = 0.000957 Kuwaiti Dinar"
            },
            {
                "title": "1 KWD = 50.416057 MVR",
                "link": "http://www.floatrates.com/kwd/mvr/",
                "description": "1 Kuwaiti Dinar = 50.416057 Maldivian rufiyaa",
                "pubDate": null,
                "baseCurrency": "KWD",
                "baseName": "Kuwaiti Dinar",
                "targetCurrency": "MVR",
                "targetName": "Maldivian rufiyaa",
                "exchangeRate": "50.416057",
                "inverseRate": "0.019835",
                "inverseDescription": "1 Maldivian rufiyaa = 0.019835 Kuwaiti Dinar"
            },
            {
                "title": "1 KWD = 147.269390 MUR",
                "link": "http://www.floatrates.com/kwd/mur/",
                "description": "1 Kuwaiti Dinar = 147.269390 Mauritian Rupee",
                "pubDate": null,
                "baseCurrency": "KWD",
                "baseName": "Kuwaiti Dinar",
                "targetCurrency": "MUR",
                "targetName": "Mauritian Rupee",
                "exchangeRate": "147.269390",
                "inverseRate": "0.006790",
                "inverseDescription": "1 Mauritian Rupee = 0.006790 Kuwaiti Dinar"
            },
            {
                "title": "1 KWD = 427.035066 NPR",
                "link": "http://www.floatrates.com/kwd/npr/",
                "description": "1 Kuwaiti Dinar = 427.035066 Nepalese Rupee",
                "pubDate": null,
                "baseCurrency": "KWD",
                "baseName": "Kuwaiti Dinar",
                "targetCurrency": "NPR",
                "targetName": "Nepalese Rupee",
                "exchangeRate": "427.035066",
                "inverseRate": "0.002342",
                "inverseDescription": "1 Nepalese Rupee = 0.002342 Kuwaiti Dinar"
            },
            {
                "title": "1 KWD = 927.680485 PKR",
                "link": "http://www.floatrates.com/kwd/pkr/",
                "description": "1 Kuwaiti Dinar = 927.680485 Pakistani Rupee",
                "pubDate": null,
                "baseCurrency": "KWD",
                "baseName": "Kuwaiti Dinar",
                "targetCurrency": "PKR",
                "targetName": "Pakistani Rupee",
                "exchangeRate": "927.680485",
                "inverseRate": "0.001078",
                "inverseDescription": "1 Pakistani Rupee = 0.001078 Kuwaiti Dinar"
            },
            {
                "title": "1 KWD = 43.081653 SCR",
                "link": "http://www.floatrates.com/kwd/scr/",
                "description": "1 Kuwaiti Dinar = 43.081653 Seychelles rupee",
                "pubDate": null,
                "baseCurrency": "KWD",
                "baseName": "Kuwaiti Dinar",
                "targetCurrency": "SCR",
                "targetName": "Seychelles rupee",
                "exchangeRate": "43.081653",
                "inverseRate": "0.023212",
                "inverseDescription": "1 Seychelles rupee = 0.023212 Kuwaiti Dinar"
            },
            {
                "title": "1 KWD = 12.139841 PEN",
                "link": "http://www.floatrates.com/kwd/pen/",
                "description": "1 Kuwaiti Dinar = 12.139841 Peruvian Nuevo Sol",
                "pubDate": null,
                "baseCurrency": "KWD",
                "baseName": "Kuwaiti Dinar",
                "targetCurrency": "PEN",
                "targetName": "Peruvian Nuevo Sol",
                "exchangeRate": "12.139841",
                "inverseRate": "0.082373",
                "inverseDescription": "1 Peruvian Nuevo Sol = 0.082373 Kuwaiti Dinar"
            },
            {
                "title": "1 KWD = 286.049153 KGS",
                "link": "http://www.floatrates.com/kwd/kgs/",
                "description": "1 Kuwaiti Dinar = 286.049153 Kyrgyzstan Som",
                "pubDate": null,
                "baseCurrency": "KWD",
                "baseName": "Kuwaiti Dinar",
                "targetCurrency": "KGS",
                "targetName": "Kyrgyzstan Som",
                "exchangeRate": "286.049153",
                "inverseRate": "0.003496",
                "inverseDescription": "1 Kyrgyzstan Som = 0.003496 Kuwaiti Dinar"
            },
            {
                "title": "1 KWD = 35.668017 TJS",
                "link": "http://www.floatrates.com/kwd/tjs/",
                "description": "1 Kuwaiti Dinar = 35.668017 Tajikistan Ruble",
                "pubDate": null,
                "baseCurrency": "KWD",
                "baseName": "Kuwaiti Dinar",
                "targetCurrency": "TJS",
                "targetName": "Tajikistan Ruble",
                "exchangeRate": "35.668017",
                "inverseRate": "0.028036",
                "inverseDescription": "1 Tajikistan Ruble = 0.028036 Kuwaiti Dinar"
            },
            {
                "title": "1 KWD = 37,253.956037 UZS",
                "link": "http://www.floatrates.com/kwd/uzs/",
                "description": "1 Kuwaiti Dinar = 37,253.956037 Uzbekistan Sum",
                "pubDate": null,
                "baseCurrency": "KWD",
                "baseName": "Kuwaiti Dinar",
                "targetCurrency": "UZS",
                "targetName": "Uzbekistan Sum",
                "exchangeRate": "37,253.956037",
                "inverseRate": "0.000027",
                "inverseDescription": "1 Uzbekistan Sum = 0.000027 Kuwaiti Dinar"
            },
            {
                "title": "1 KWD = 443.510292 KES",
                "link": "http://www.floatrates.com/kwd/kes/",
                "description": "1 Kuwaiti Dinar = 443.510292 Kenyan shilling",
                "pubDate": null,
                "baseCurrency": "KWD",
                "baseName": "Kuwaiti Dinar",
                "targetCurrency": "KES",
                "targetName": "Kenyan shilling",
                "exchangeRate": "443.510292",
                "inverseRate": "0.002255",
                "inverseDescription": "1 Kenyan shilling = 0.002255 Kuwaiti Dinar"
            },
            {
                "title": "1 KWD = 1,853.894749 SOS",
                "link": "http://www.floatrates.com/kwd/sos/",
                "description": "1 Kuwaiti Dinar = 1,853.894749 Somali shilling",
                "pubDate": null,
                "baseCurrency": "KWD",
                "baseName": "Kuwaiti Dinar",
                "targetCurrency": "SOS",
                "targetName": "Somali shilling",
                "exchangeRate": "1,853.894749",
                "inverseRate": "0.000539",
                "inverseDescription": "1 Somali shilling = 0.000539 Kuwaiti Dinar"
            },
            {
                "title": "1 KWD = 7,683.259232 TZS",
                "link": "http://www.floatrates.com/kwd/tzs/",
                "description": "1 Kuwaiti Dinar = 7,683.259232 Tanzanian shilling",
                "pubDate": null,
                "baseCurrency": "KWD",
                "baseName": "Kuwaiti Dinar",
                "targetCurrency": "TZS",
                "targetName": "Tanzanian shilling",
                "exchangeRate": "7,683.259232",
                "inverseRate": "0.000130",
                "inverseDescription": "1 Tanzanian shilling = 0.000130 Kuwaiti Dinar"
            },
            {
                "title": "1 KWD = 12,206.468296 UGX",
                "link": "http://www.floatrates.com/kwd/ugx/",
                "description": "1 Kuwaiti Dinar = 12,206.468296 Ugandan shilling",
                "pubDate": null,
                "baseCurrency": "KWD",
                "baseName": "Kuwaiti Dinar",
                "targetCurrency": "UGX",
                "targetName": "Ugandan shilling",
                "exchangeRate": "12,206.468296",
                "inverseRate": "0.000082",
                "inverseDescription": "1 Ugandan shilling = 0.000082 Kuwaiti Dinar"
            },
            {
                "title": "1 KWD = 349.237115 BDT",
                "link": "http://www.floatrates.com/kwd/bdt/",
                "description": "1 Kuwaiti Dinar = 349.237115 Bangladeshi taka",
                "pubDate": null,
                "baseCurrency": "KWD",
                "baseName": "Kuwaiti Dinar",
                "targetCurrency": "BDT",
                "targetName": "Bangladeshi taka",
                "exchangeRate": "349.237115",
                "inverseRate": "0.002863",
                "inverseDescription": "1 Bangladeshi taka = 0.002863 Kuwaiti Dinar"
            },
            {
                "title": "1 KWD = 8.890177 WST",
                "link": "http://www.floatrates.com/kwd/wst/",
                "description": "1 Kuwaiti Dinar = 8.890177 Samoan tala",
                "pubDate": null,
                "baseCurrency": "KWD",
                "baseName": "Kuwaiti Dinar",
                "targetCurrency": "WST",
                "targetName": "Samoan tala",
                "exchangeRate": "8.890177",
                "inverseRate": "0.112484",
                "inverseDescription": "1 Samoan tala = 0.112484 Kuwaiti Dinar"
            },
            {
                "title": "1 KWD = 1,456.556541 KZT",
                "link": "http://www.floatrates.com/kwd/kzt/",
                "description": "1 Kuwaiti Dinar = 1,456.556541 Kazakhstani Tenge",
                "pubDate": null,
                "baseCurrency": "KWD",
                "baseName": "Kuwaiti Dinar",
                "targetCurrency": "KZT",
                "targetName": "Kazakhstani Tenge",
                "exchangeRate": "1,456.556541",
                "inverseRate": "0.000687",
                "inverseDescription": "1 Kazakhstani Tenge = 0.000687 Kuwaiti Dinar"
            },
            {
                "title": "1 KWD = 11,399.513488 MNT",
                "link": "http://www.floatrates.com/kwd/mnt/",
                "description": "1 Kuwaiti Dinar = 11,399.513488 Mongolian togrog",
                "pubDate": null,
                "baseCurrency": "KWD",
                "baseName": "Kuwaiti Dinar",
                "targetCurrency": "MNT",
                "targetName": "Mongolian togrog",
                "exchangeRate": "11,399.513488",
                "inverseRate": "0.000088",
                "inverseDescription": "1 Mongolian togrog = 0.000088 Kuwaiti Dinar"
            },
            {
                "title": "1 KWD = 391.145336 VUV",
                "link": "http://www.floatrates.com/kwd/vuv/",
                "description": "1 Kuwaiti Dinar = 391.145336 Vanuatu vatu",
                "pubDate": null,
                "baseCurrency": "KWD",
                "baseName": "Kuwaiti Dinar",
                "targetCurrency": "VUV",
                "targetName": "Vanuatu vatu",
                "exchangeRate": "391.145336",
                "inverseRate": "0.002557",
                "inverseDescription": "1 Vanuatu vatu = 0.002557 Kuwaiti Dinar"
            },
            {
                "title": "1 KWD = 5.820054 BAM",
                "link": "http://www.floatrates.com/kwd/bam/",
                "description": "1 Kuwaiti Dinar = 5.820054 Bosnia and Herzegovina convertible mark",
                "pubDate": null,
                "baseCurrency": "KWD",
                "baseName": "Kuwaiti Dinar",
                "targetCurrency": "BAM",
                "targetName": "Bosnia and Herzegovina convertible mark",
                "exchangeRate": "5.820054",
                "inverseRate": "0.171820",
                "inverseDescription": "1 Bosnia and Herzegovina convertible mark = 0.171820 Kuwaiti Dinar"
            },
            {
                "title": "1 KWD = 13.606720 PLN",
                "link": "http://www.floatrates.com/kwd/pln/",
                "description": "1 Kuwaiti Dinar = 13.606720 Polish Zloty",
                "pubDate": null,
                "baseCurrency": "KWD",
                "baseName": "Kuwaiti Dinar",
                "targetCurrency": "PLN",
                "targetName": "Polish Zloty",
                "exchangeRate": "13.606720",
                "inverseRate": "0.073493",
                "inverseDescription": "1 Polish Zloty = 0.073493 Kuwaiti Dinar"
            },
            {
                "title": "1 KWD = 24.904667 HRK",
                "link": "http://www.floatrates.com/kwd/hrk/",
                "description": "1 Kuwaiti Dinar = 24.904667 Croatian Kuna",
                "pubDate": null,
                "baseCurrency": "KWD",
                "baseName": "Kuwaiti Dinar",
                "targetCurrency": "HRK",
                "targetName": "Croatian Kuna",
                "exchangeRate": "24.904667",
                "inverseRate": "0.040153",
                "inverseDescription": "1 Croatian Kuna = 0.040153 Kuwaiti Dinar"
            }
        ]
    }
}